{"season":2026,"updated":"2026-05-06T17:37:02Z","lg_xwoba":0.32,"players":{"687263":{"name":"Zach Neto","xwoba":0.315,"pa":171,"type":"batter"},"695578":{"name":"James Wood","xwoba":0.42,"pa":171,"type":"batter"},"686948":{"name":"Drake Baldwin","xwoba":0.396,"pa":170,"type":"batter"},"670541":{"name":"Yordan Alvarez","xwoba":0.504,"pa":166,"type":"batter"},"621566":{"name":"Matt Olson","xwoba":0.413,"pa":166,"type":"batter"},"545361":{"name":"Mike Trout","xwoba":0.461,"pa":165,"type":"batter"},"608324":{"name":"Alex Bregman","xwoba":0.335,"pa":165,"type":"batter"},"683002":{"name":"Gunnar Henderson","xwoba":0.298,"pa":163,"type":"batter"},"663538":{"name":"Nico Hoerner","xwoba":0.349,"pa":162,"type":"batter"},"677951":{"name":"Bobby Witt Jr.","xwoba":0.387,"pa":162,"type":"batter"},"671056":{"name":"Iv\u00e1n Herrera","xwoba":0.38,"pa":161,"type":"batter"},"621493":{"name":"Taylor Ward","xwoba":0.382,"pa":161,"type":"batter"},"677594":{"name":"Julio Rodr\u00edguez","xwoba":0.328,"pa":161,"type":"batter"},"656941":{"name":"Kyle Schwarber","xwoba":0.369,"pa":161,"type":"batter"},"802139":{"name":"JJ Wetherholt","xwoba":0.361,"pa":161,"type":"batter"},"608070":{"name":"Jos\u00e9 Ram\u00edrez","xwoba":0.371,"pa":161,"type":"batter"},"805300":{"name":"Jakob Marsee","xwoba":0.277,"pa":160,"type":"batter"},"668804":{"name":"Bryan Reynolds","xwoba":0.353,"pa":160,"type":"batter"},"682829":{"name":"Elly De La Cruz","xwoba":0.367,"pa":159,"type":"batter"},"645277":{"name":"Ozzie Albies","xwoba":0.322,"pa":159,"type":"batter"},"592450":{"name":"Aaron Judge","xwoba":0.454,"pa":159,"type":"batter"},"660271":{"name":"Shohei Ohtani","xwoba":0.236,"pa":145,"type":"pitcher"},"701762":{"name":"Nick Kurtz","xwoba":0.386,"pa":157,"type":"batter"},"666176":{"name":"Jo Adell","xwoba":0.309,"pa":157,"type":"batter"},"607208":{"name":"Trea Turner","xwoba":0.288,"pa":157,"type":"batter"},"664023":{"name":"Ian Happ","xwoba":0.352,"pa":156,"type":"batter"},"663586":{"name":"Austin Riley","xwoba":0.298,"pa":156,"type":"batter"},"665833":{"name":"Oneil Cruz","xwoba":0.365,"pa":156,"type":"batter"},"808959":{"name":"Munetaka Murakami","xwoba":0.402,"pa":156,"type":"batter"},"624413":{"name":"Pete Alonso","xwoba":0.359,"pa":155,"type":"batter"},"678246":{"name":"Miguel Vargas","xwoba":0.378,"pa":155,"type":"batter"},"663656":{"name":"Kyle Tucker","xwoba":0.322,"pa":155,"type":"batter"},"695734":{"name":"Daylen Lile","xwoba":0.336,"pa":155,"type":"batter"},"701398":{"name":"Sal Stewart","xwoba":0.377,"pa":155,"type":"batter"},"805808":{"name":"Kevin McGonigle","xwoba":0.397,"pa":154,"type":"batter"},"668227":{"name":"Randy Arozarena","xwoba":0.325,"pa":154,"type":"batter"},"669364":{"name":"Xavier Edwards","xwoba":0.365,"pa":154,"type":"batter"},"547180":{"name":"Bryce Harper","xwoba":0.406,"pa":154,"type":"batter"},"666182":{"name":"Bo Bichette","xwoba":0.316,"pa":154,"type":"batter"},"683737":{"name":"Michael Busch","xwoba":0.312,"pa":154,"type":"batter"},"682985":{"name":"Riley Greene","xwoba":0.388,"pa":153,"type":"batter"},"680757":{"name":"Steven Kwan","xwoba":0.281,"pa":153,"type":"batter"},"621439":{"name":"Byron Buxton","xwoba":0.319,"pa":153,"type":"batter"},"660670":{"name":"Ronald Acu\u00f1a Jr.","xwoba":0.381,"pa":152,"type":"batter"},"676475":{"name":"Alec Burleson","xwoba":0.384,"pa":152,"type":"batter"},"575929":{"name":"Willson Contreras","xwoba":0.415,"pa":152,"type":"batter"},"572233":{"name":"Christian Walker","xwoba":0.369,"pa":151,"type":"batter"},"514888":{"name":"Jose Altuve","xwoba":0.31,"pa":151,"type":"batter"},"641355":{"name":"Cody Bellinger","xwoba":0.383,"pa":151,"type":"batter"},"691406":{"name":"Junior Caminero","xwoba":0.361,"pa":151,"type":"batter"},"663728":{"name":"Cal Raleigh","xwoba":0.314,"pa":151,"type":"batter"},"672640":{"name":"Otto Lopez","xwoba":0.351,"pa":150,"type":"batter"},"518692":{"name":"Freddie Freeman","xwoba":0.383,"pa":150,"type":"batter"},"695657":{"name":"Colson Montgomery","xwoba":0.33,"pa":150,"type":"batter"},"802415":{"name":"Chandler Simpson","xwoba":0.266,"pa":150,"type":"batter"},"666018":{"name":"Jonathan Aranda","xwoba":0.354,"pa":150,"type":"batter"},"677800":{"name":"Wilyer Abreu","xwoba":0.376,"pa":150,"type":"batter"},"665489":{"name":"Vladimir Guerrero Jr.","xwoba":0.377,"pa":150,"type":"batter"},"656305":{"name":"Matt Chapman","xwoba":0.27,"pa":149,"type":"batter"},"672580":{"name":"Maikel Garcia","xwoba":0.333,"pa":149,"type":"batter"},"805367":{"name":"Chase Meidroth","xwoba":0.301,"pa":149,"type":"batter"},"596115":{"name":"Trevor Story","xwoba":0.259,"pa":149,"type":"batter"},"805779":{"name":"Jacob Wilson","xwoba":0.274,"pa":148,"type":"batter"},"665487":{"name":"Fernando Tatis Jr.","xwoba":0.352,"pa":148,"type":"batter"},"691718":{"name":"Pete Crow-Armstrong","xwoba":0.304,"pa":148,"type":"batter"},"608369":{"name":"Corey Seager","xwoba":0.348,"pa":148,"type":"batter"},"642715":{"name":"Willy Adames","xwoba":0.263,"pa":148,"type":"batter"},"646240":{"name":"Rafael Devers","xwoba":0.259,"pa":148,"type":"batter"},"807712":{"name":"Luke Keaschall","xwoba":0.284,"pa":148,"type":"batter"},"607043":{"name":"Brandon Nimmo","xwoba":0.368,"pa":147,"type":"batter"},"672960":{"name":"Kazuma Okamoto","xwoba":0.362,"pa":147,"type":"batter"},"680574":{"name":"Matt McLain","xwoba":0.309,"pa":147,"type":"batter"},"676391":{"name":"Ernie Clement","xwoba":0.28,"pa":147,"type":"batter"},"682928":{"name":"CJ Abrams","xwoba":0.381,"pa":147,"type":"batter"},"521692":{"name":"Salvador Perez","xwoba":0.276,"pa":147,"type":"batter"},"647304":{"name":"Josh Naylor","xwoba":0.319,"pa":147,"type":"batter"},"669394":{"name":"Jake Burger","xwoba":0.275,"pa":146,"type":"batter"},"686469":{"name":"Vinnie Pasquantino","xwoba":0.311,"pa":146,"type":"batter"},"694384":{"name":"Nolan Schanuel","xwoba":0.306,"pa":146,"type":"batter"},"691023":{"name":"Jordan Walker","xwoba":0.405,"pa":146,"type":"batter"},"669127":{"name":"Shea Langeliers","xwoba":0.413,"pa":146,"type":"batter"},"701538":{"name":"Jackson Merrill","xwoba":0.316,"pa":145,"type":"batter"},"702284":{"name":"Cole Young","xwoba":0.33,"pa":145,"type":"batter"},"681624":{"name":"Andy Pages","xwoba":0.347,"pa":144,"type":"batter"},"701358":{"name":"Cam Smith","xwoba":0.348,"pa":144,"type":"batter"},"650333":{"name":"Luis Arraez","xwoba":0.302,"pa":144,"type":"batter"},"650402":{"name":"Gleyber Torres","xwoba":0.347,"pa":144,"type":"batter"},"681198":{"name":"TJ Rumfield","xwoba":0.336,"pa":144,"type":"batter"},"668930":{"name":"Brice Turang","xwoba":0.426,"pa":144,"type":"batter"},"650490":{"name":"Yandy D\u00edaz","xwoba":0.369,"pa":143,"type":"batter"},"656811":{"name":"Ryan O'Hearn","xwoba":0.375,"pa":143,"type":"batter"},"661388":{"name":"William Contreras","xwoba":0.354,"pa":143,"type":"batter"},"665862":{"name":"Jazz Chisholm Jr.","xwoba":0.287,"pa":143,"type":"batter"},"691016":{"name":"Tyler Soderstrom","xwoba":0.334,"pa":142,"type":"batter"},"621020":{"name":"Dansby Swanson","xwoba":0.349,"pa":142,"type":"batter"},"666969":{"name":"Adolis Garc\u00eda","xwoba":0.325,"pa":142,"type":"batter"},"593428":{"name":"Xander Bogaerts","xwoba":0.348,"pa":142,"type":"batter"},"624585":{"name":"Jorge Soler","xwoba":0.324,"pa":142,"type":"batter"},"670770":{"name":"TJ Friedl","xwoba":0.252,"pa":142,"type":"batter"},"621043":{"name":"Carlos Correa","xwoba":0.365,"pa":141,"type":"batter"},"808982":{"name":"Jung Hoo Lee","xwoba":0.316,"pa":141,"type":"batter"},"606466":{"name":"Ketel Marte","xwoba":0.363,"pa":141,"type":"batter"},"679529":{"name":"Spencer Torkelson","xwoba":0.36,"pa":140,"type":"batter"},"605137":{"name":"Josh Bell","xwoba":0.323,"pa":140,"type":"batter"},"592518":{"name":"Manny Machado","xwoba":0.318,"pa":139,"type":"batter"},"664761":{"name":"Alec Bohm","xwoba":0.271,"pa":139,"type":"batter"},"643289":{"name":"Mauricio Dub\u00f3n","xwoba":0.317,"pa":139,"type":"batter"},"671218":{"name":"Heliot Ramos","xwoba":0.327,"pa":138,"type":"batter"},"696100":{"name":"Hunter Goodman","xwoba":0.312,"pa":138,"type":"batter"},"663757":{"name":"Trent Grisham","xwoba":0.371,"pa":137,"type":"batter"},"571970":{"name":"Max Muncy","xwoba":0.414,"pa":136,"type":"batter"},"657656":{"name":"Ram\u00f3n Laureano","xwoba":0.325,"pa":136,"type":"batter"},"543760":{"name":"Marcus Semien","xwoba":0.278,"pa":136,"type":"batter"},"678662":{"name":"Ezequiel Tovar","xwoba":0.293,"pa":135,"type":"batter"},"664040":{"name":"Brandon Lowe","xwoba":0.367,"pa":135,"type":"batter"},"700250":{"name":"Ben Rice","xwoba":0.459,"pa":134,"type":"batter"},"800050":{"name":"Chase DeLauter","xwoba":0.378,"pa":134,"type":"batter"},"682998":{"name":"Corbin Carroll","xwoba":0.343,"pa":134,"type":"batter"},"670623":{"name":"Isaac Paredes","xwoba":0.319,"pa":133,"type":"batter"},"680776":{"name":"Jarren Duran","xwoba":0.296,"pa":132,"type":"batter"},"676609":{"name":"Jos\u00e9 Caballero","xwoba":0.268,"pa":132,"type":"batter"},"606192":{"name":"Teoscar Hern\u00e1ndez","xwoba":0.318,"pa":131,"type":"batter"},"673962":{"name":"Josh Jung","xwoba":0.372,"pa":131,"type":"batter"},"662139":{"name":"Daulton Varsho","xwoba":0.31,"pa":131,"type":"batter"},"669357":{"name":"Nolan Gorman","xwoba":0.296,"pa":130,"type":"batter"},"693304":{"name":"Nick Gonzales","xwoba":0.338,"pa":130,"type":"batter"},"677587":{"name":"Brayan Rocchio","xwoba":0.303,"pa":130,"type":"batter"},"701350":{"name":"Roman Anthony","xwoba":0.353,"pa":130,"type":"batter"},"682663":{"name":"Agust\u00edn Ram\u00edrez","xwoba":0.283,"pa":129,"type":"batter"},"672695":{"name":"Geraldo Perdomo","xwoba":0.325,"pa":129,"type":"batter"},"691026":{"name":"Masyn Winn","xwoba":0.316,"pa":129,"type":"batter"},"668715":{"name":"Spencer Steer","xwoba":0.369,"pa":128,"type":"batter"},"691781":{"name":"Brady House","xwoba":0.305,"pa":128,"type":"batter"},"678882":{"name":"Ceddanne Rafaela","xwoba":0.299,"pa":127,"type":"batter"},"702332":{"name":"Caleb Durbin","xwoba":0.27,"pa":127,"type":"batter"},"665926":{"name":"Andr\u00e9s Gim\u00e9nez","xwoba":0.26,"pa":127,"type":"batter"},"641343":{"name":"Jake Bauers","xwoba":0.331,"pa":126,"type":"batter"},"694497":{"name":"Evan Carter","xwoba":0.311,"pa":126,"type":"batter"},"686217":{"name":"Sal Frelick","xwoba":0.308,"pa":125,"type":"batter"},"542303":{"name":"Marcell Ozuna","xwoba":0.308,"pa":125,"type":"batter"},"641487":{"name":"J.P. Crawford","xwoba":0.378,"pa":124,"type":"batter"},"686797":{"name":"Brooks Lee","xwoba":0.264,"pa":124,"type":"batter"},"669016":{"name":"Brandon Marsh","xwoba":0.339,"pa":123,"type":"batter"},"681393":{"name":"Connor Norby","xwoba":0.304,"pa":123,"type":"batter"},"695600":{"name":"Carter Jensen","xwoba":0.304,"pa":123,"type":"batter"},"696285":{"name":"Jacob Young","xwoba":0.293,"pa":123,"type":"batter"},"693307":{"name":"Dillon Dingler","xwoba":0.422,"pa":122,"type":"batter"},"660821":{"name":"Jes\u00fas S\u00e1nchez","xwoba":0.327,"pa":122,"type":"batter"},"689414":{"name":"Liam Hicks","xwoba":0.381,"pa":121,"type":"batter"},"669477":{"name":"Casey Schmitt","xwoba":0.38,"pa":121,"type":"batter"},"683083":{"name":"Nasim Nu\u00f1ez","xwoba":0.287,"pa":120,"type":"batter"},"571448":{"name":"Nolan Arenado","xwoba":0.312,"pa":120,"type":"batter"},"687859":{"name":"Troy Johnston","xwoba":0.318,"pa":119,"type":"batter"},"656775":{"name":"Cedric Mullins","xwoba":0.216,"pa":119,"type":"batter"},"669003":{"name":"Garrett Mitchell","xwoba":0.335,"pa":119,"type":"batter"},"695506":{"name":"Jac Caglianone","xwoba":0.331,"pa":118,"type":"batter"},"691720":{"name":"Kyle Karros","xwoba":0.35,"pa":118,"type":"batter"},"671739":{"name":"Michael Harris II","xwoba":0.439,"pa":118,"type":"batter"},"670242":{"name":"Matt Wallner","xwoba":0.294,"pa":117,"type":"batter"},"643217":{"name":"Andrew Benintendi","xwoba":0.303,"pa":117,"type":"batter"},"643446":{"name":"Jeff McNeil","xwoba":0.34,"pa":117,"type":"batter"},"804606":{"name":"Konnor Griffin","xwoba":0.327,"pa":117,"type":"batter"},"669236":{"name":"Jeremiah Jackson","xwoba":0.295,"pa":116,"type":"batter"},"669257":{"name":"Will Smith","xwoba":0.373,"pa":116,"type":"batter"},"682657":{"name":"Angel Mart\u00ednez","xwoba":0.327,"pa":116,"type":"batter"},"687462":{"name":"Spencer Horwitz","xwoba":0.298,"pa":116,"type":"batter"},"573262":{"name":"Mike Yastrzemski","xwoba":0.261,"pa":116,"type":"batter"},"630105":{"name":"Jake Cronenworth","xwoba":0.305,"pa":114,"type":"batter"},"702222":{"name":"Justin Crawford","xwoba":0.285,"pa":114,"type":"batter"},"681082":{"name":"Bryson Stott","xwoba":0.297,"pa":114,"type":"batter"},"545121":{"name":"Ildemaro Vargas","xwoba":0.372,"pa":113,"type":"batter"},"681481":{"name":"Kerry Carpenter","xwoba":0.309,"pa":113,"type":"batter"},"650859":{"name":"Luis Rengifo","xwoba":0.278,"pa":112,"type":"batter"},"671277":{"name":"Luis Garc\u00eda Jr.","xwoba":0.302,"pa":112,"type":"batter"},"683146":{"name":"Brett Baty","xwoba":0.281,"pa":112,"type":"batter"},"671732":{"name":"Lawrence Butler","xwoba":0.303,"pa":112,"type":"batter"},"686555":{"name":"Isaac Collins","xwoba":0.314,"pa":112,"type":"batter"},"700932":{"name":"Kyle Manzardo","xwoba":0.285,"pa":111,"type":"batter"},"660162":{"name":"Yo\u00e1n Moncada","xwoba":0.274,"pa":111,"type":"batter"},"666160":{"name":"Mickey Moniak","xwoba":0.354,"pa":111,"type":"batter"},"680777":{"name":"Ryan Jeffers","xwoba":0.377,"pa":110,"type":"batter"},"682626":{"name":"Francisco Alvarez","xwoba":0.332,"pa":110,"type":"batter"},"701807":{"name":"Carson Benge","xwoba":0.304,"pa":109,"type":"batter"},"669701":{"name":"Josh Smith","xwoba":0.301,"pa":108,"type":"batter"},"701675":{"name":"Nathan Church","xwoba":0.314,"pa":108,"type":"batter"},"694212":{"name":"Samuel Basallo","xwoba":0.331,"pa":108,"type":"batter"},"683357":{"name":"Owen Caissie","xwoba":0.275,"pa":107,"type":"batter"},"690993":{"name":"Colt Keith","xwoba":0.346,"pa":107,"type":"batter"},"673237":{"name":"Yainer Diaz","xwoba":0.257,"pa":106,"type":"batter"},"660844":{"name":"Leo Rivas","xwoba":0.238,"pa":106,"type":"batter"},"596019":{"name":"Francisco Lindor","xwoba":0.341,"pa":105,"type":"batter"},"810938":{"name":"Ben Williamson","xwoba":0.544,"pa":4,"type":"pitcher"},"669224":{"name":"Austin Wells","xwoba":0.339,"pa":104,"type":"batter"},"691777":{"name":"Max Muncy","xwoba":0.303,"pa":104,"type":"batter"},"657757":{"name":"Gavin Sheets","xwoba":0.303,"pa":104,"type":"batter"},"687363":{"name":"Victor Scott II","xwoba":0.26,"pa":103,"type":"batter"},"666152":{"name":"David Hamilton","xwoba":0.293,"pa":103,"type":"batter"},"687637":{"name":"Dylan Beavers","xwoba":0.304,"pa":103,"type":"batter"},"672724":{"name":"Oswald Peraza","xwoba":0.322,"pa":103,"type":"batter"},"666397":{"name":"Edouard Julien","xwoba":0.354,"pa":102,"type":"batter"},"666139":{"name":"Josh Lowe","xwoba":0.255,"pa":102,"type":"batter"},"656555":{"name":"Rhys Hoskins","xwoba":0.309,"pa":102,"type":"batter"},"650489":{"name":"Willi Castro","xwoba":0.279,"pa":102,"type":"batter"},"673548":{"name":"Seiya Suzuki","xwoba":0.386,"pa":101,"type":"batter"},"691785":{"name":"Marcelo Mayer","xwoba":0.298,"pa":101,"type":"batter"},"663886":{"name":"Tyler Stephenson","xwoba":0.337,"pa":101,"type":"batter"},"682177":{"name":"Daniel Schneemann","xwoba":0.338,"pa":101,"type":"batter"},"670042":{"name":"Luke Raley","xwoba":0.385,"pa":101,"type":"batter"},"605170":{"name":"Victor Caratini","xwoba":0.342,"pa":101,"type":"batter"},"686668":{"name":"Brenton Doyle","xwoba":0.252,"pa":100,"type":"batter"},"608348":{"name":"Carson Kelly","xwoba":0.351,"pa":100,"type":"batter"},"668885":{"name":"Austin Martin","xwoba":0.375,"pa":100,"type":"batter"},"553993":{"name":"Eugenio Su\u00e1rez","xwoba":0.273,"pa":100,"type":"batter"},"690976":{"name":"Alex Freeland","xwoba":0.306,"pa":100,"type":"batter"},"673357":{"name":"Luis Robert Jr.","xwoba":0.324,"pa":98,"type":"batter"},"691723":{"name":"Coby Mayo","xwoba":0.274,"pa":98,"type":"batter"},"664728":{"name":"Kyle Isbel","xwoba":0.314,"pa":98,"type":"batter"},"641857":{"name":"Ryan McMahon","xwoba":0.298,"pa":98,"type":"batter"},"663647":{"name":"Ke'Bryan Hayes","xwoba":0.302,"pa":98,"type":"batter"},"663616":{"name":"Trevor Larnach","xwoba":0.339,"pa":98,"type":"batter"},"694208":{"name":"Mois\u00e9s Ballesteros","xwoba":0.356,"pa":97,"type":"batter"},"699912":{"name":"Jose Fernandez","xwoba":0.304,"pa":97,"type":"batter"},"677950":{"name":"Alek Thomas","xwoba":0.29,"pa":96,"type":"batter"},"519317":{"name":"Giancarlo Stanton","xwoba":0.326,"pa":96,"type":"batter"},"592626":{"name":"Joc Pederson","xwoba":0.309,"pa":96,"type":"batter"},"665750":{"name":"Leody Taveras","xwoba":0.364,"pa":95,"type":"batter"},"665019":{"name":"Kody Clemens","xwoba":0.345,"pa":95,"type":"batter"},"668901":{"name":"Mark Vientos","xwoba":0.349,"pa":95,"type":"batter"},"700337":{"name":"Edgar Quero","xwoba":0.246,"pa":93,"type":"batter"},"681351":{"name":"Logan O'Hoppe","xwoba":0.294,"pa":93,"type":"batter"},"663604":{"name":"Brandon Lockridge","xwoba":0.267,"pa":93,"type":"batter"},"663743":{"name":"Nick Fortes","xwoba":0.301,"pa":92,"type":"batter"},"609280":{"name":"Miguel Andujar","xwoba":0.303,"pa":91,"type":"batter"},"596142":{"name":"Gary S\u00e1nchez","xwoba":0.379,"pa":89,"type":"batter"},"668904":{"name":"Royce Lewis","xwoba":0.296,"pa":89,"type":"batter"},"677942":{"name":"Blaze Alexander","xwoba":0.315,"pa":89,"type":"batter"},"807713":{"name":"Matt Shaw","xwoba":0.309,"pa":88,"type":"batter"},"682668":{"name":"Luisangel Acu\u00f1a","xwoba":0.272,"pa":88,"type":"batter"},"671976":{"name":"Tristan Peters","xwoba":0.28,"pa":87,"type":"batter"},"663837":{"name":"Matt Vierling","xwoba":0.293,"pa":86,"type":"batter"},"672275":{"name":"Patrick Bailey","xwoba":0.292,"pa":86,"type":"batter"},"678391":{"name":"Jorbit Vivas","xwoba":0.277,"pa":86,"type":"batter"},"665742":{"name":"Juan Soto","xwoba":0.43,"pa":86,"type":"batter"},"666310":{"name":"Bo Naylor","xwoba":0.288,"pa":85,"type":"batter"},"678554":{"name":"Curtis Mead","xwoba":0.352,"pa":85,"type":"batter"},"643376":{"name":"Danny Jansen","xwoba":0.25,"pa":85,"type":"batter"},"670764":{"name":"Taylor Walls","xwoba":0.227,"pa":85,"type":"batter"},"686527":{"name":"Dominic Canzone","xwoba":0.376,"pa":84,"type":"batter"},"680779":{"name":"Henry Davis","xwoba":0.266,"pa":84,"type":"batter"},"666126":{"name":"Carlos Cortes","xwoba":0.428,"pa":84,"type":"batter"},"686780":{"name":"Pedro Pag\u00e9s","xwoba":0.287,"pa":84,"type":"batter"},"694671":{"name":"Wyatt Langford","xwoba":0.282,"pa":84,"type":"batter"},"687401":{"name":"Joey Ortiz","xwoba":0.273,"pa":83,"type":"batter"},"595879":{"name":"Javier B\u00e1ez","xwoba":0.294,"pa":82,"type":"batter"},"663968":{"name":"Jake Mangum","xwoba":0.286,"pa":82,"type":"batter"},"677649":{"name":"Ezequiel Duran","xwoba":0.318,"pa":82,"type":"batter"},"668939":{"name":"Adley Rutschman","xwoba":0.319,"pa":82,"type":"batter"},"694728":{"name":"Brice Matthews","xwoba":0.284,"pa":81,"type":"batter"},"688363":{"name":"Graham Pauley","xwoba":0.197,"pa":81,"type":"batter"},"667670":{"name":"Brent Rooker","xwoba":0.291,"pa":81,"type":"batter"},"672820":{"name":"Lenyn Sosa","xwoba":0.278,"pa":80,"type":"batter"},"543807":{"name":"George Springer","xwoba":0.317,"pa":80,"type":"batter"},"681297":{"name":"Colton Cowser","xwoba":0.274,"pa":79,"type":"batter"},"657041":{"name":"Lane Thomas","xwoba":0.323,"pa":79,"type":"batter"},"665966":{"name":"Carlos Narv\u00e1ez","xwoba":0.275,"pa":78,"type":"batter"},"694377":{"name":"Nick Yorke","xwoba":0.329,"pa":78,"type":"batter"},"641584":{"name":"Jake Fraley","xwoba":0.293,"pa":78,"type":"batter"},"642086":{"name":"Dominic Smith","xwoba":0.385,"pa":77,"type":"batter"},"676356":{"name":"Jonny DeLuca","xwoba":0.297,"pa":77,"type":"batter"},"663993":{"name":"Nathaniel Lowe","xwoba":0.404,"pa":77,"type":"batter"},"691594":{"name":"Javier Sanoja","xwoba":0.26,"pa":76,"type":"batter"},"678489":{"name":"Jorge Barrosa","xwoba":0.226,"pa":76,"type":"batter"},"681715":{"name":"Heriberto Hern\u00e1ndez","xwoba":0.295,"pa":74,"type":"batter"},"687597":{"name":"Jordan Beck","xwoba":0.258,"pa":74,"type":"batter"},"664983":{"name":"Jake McCarthy","xwoba":0.313,"pa":73,"type":"batter"},"808975":{"name":"Hyeseong Kim","xwoba":0.344,"pa":73,"type":"batter"},"671289":{"name":"Tyler Freeman","xwoba":0.348,"pa":73,"type":"batter"},"592663":{"name":"J.T. Realmuto","xwoba":0.294,"pa":72,"type":"batter"},"677592":{"name":"Everson Pereira","xwoba":0.314,"pa":71,"type":"batter"},"680728":{"name":"Adrian Del Castillo","xwoba":0.272,"pa":71,"type":"batter"},"680977":{"name":"Brendan Donovan","xwoba":0.339,"pa":71,"type":"batter"},"803011":{"name":"Sam Antonacci","xwoba":0.406,"pa":70,"type":"batter"},"686681":{"name":"Michael Massey","xwoba":0.271,"pa":70,"type":"batter"},"660688":{"name":"Keibert Ruiz","xwoba":0.208,"pa":69,"type":"batter"},"672761":{"name":"Wenceel P\u00e9rez","xwoba":0.312,"pa":69,"type":"batter"},"592206":{"name":"Nick Castellanos","xwoba":0.297,"pa":69,"type":"batter"},"602104":{"name":"Ram\u00f3n Ur\u00edas","xwoba":0.307,"pa":68,"type":"batter"},"666023":{"name":"Freddy Fermin","xwoba":0.272,"pa":68,"type":"batter"},"642708":{"name":"Amed Rosario","xwoba":0.378,"pa":67,"type":"batter"},"624428":{"name":"Adam Frazier","xwoba":0.408,"pa":3,"type":"pitcher"},"543877":{"name":"Christian V\u00e1zquez","xwoba":0.249,"pa":66,"type":"batter"},"665804":{"name":"Miguel Amaya","xwoba":0.305,"pa":66,"type":"batter"},"680700":{"name":"Richie Palacios","xwoba":0.343,"pa":66,"type":"batter"},"694388":{"name":"Joey Loperfido","xwoba":0.279,"pa":66,"type":"batter"},"686894":{"name":"Joey Wiemer","xwoba":0.433,"pa":7,"type":"pitcher"},"621438":{"name":"Tyrone Taylor","xwoba":0.257,"pa":65,"type":"batter"},"676914":{"name":"Davis Schneider","xwoba":0.302,"pa":65,"type":"batter"},"807799":{"name":"Masataka Yoshida","xwoba":0.289,"pa":65,"type":"batter"},"664702":{"name":"Myles Straw","xwoba":0.37,"pa":64,"type":"batter"},"677588":{"name":"Jos\u00e9 Tena","xwoba":0.301,"pa":64,"type":"batter"},"669065":{"name":"Kyle Stowers","xwoba":0.302,"pa":62,"type":"batter"},"687231":{"name":"Darell Hernaiz","xwoba":0.249,"pa":61,"type":"batter"},"656484":{"name":"Tristan Gray","xwoba":0.3,"pa":61,"type":"batter"},"666181":{"name":"Will Benson","xwoba":0.294,"pa":61,"type":"batter"},"686452":{"name":"Drew Millas","xwoba":0.242,"pa":61,"type":"batter"},"593871":{"name":"Jorge Polanco","xwoba":0.27,"pa":61,"type":"batter"},"687093":{"name":"Vaughn Grissom","xwoba":0.338,"pa":60,"type":"batter"},"687221":{"name":"Dalton Rushing","xwoba":0.403,"pa":60,"type":"batter"},"500743":{"name":"Miguel Rojas","xwoba":0.384,"pa":6,"type":"pitcher"},"655316":{"name":"Andruw Monasterio","xwoba":0.323,"pa":60,"type":"batter"},"672016":{"name":"Denzel Clarke","xwoba":0.193,"pa":60,"type":"batter"},"672515":{"name":"Gabriel Moreno","xwoba":0.346,"pa":58,"type":"batter"},"669134":{"name":"Luis Campusano","xwoba":0.341,"pa":58,"type":"batter"},"687551":{"name":"Drew Gilbert","xwoba":0.261,"pa":58,"type":"batter"},"663697":{"name":"Jonathan India","xwoba":0.286,"pa":58,"type":"batter"},"623168":{"name":"Tyler Heineman","xwoba":0.509,"pa":17,"type":"pitcher"},"695336":{"name":"Thomas Saggese","xwoba":0.215,"pa":57,"type":"batter"},"642201":{"name":"Eli White","xwoba":0.276,"pa":57,"type":"batter"},"592885":{"name":"Christian Yelich","xwoba":0.282,"pa":56,"type":"batter"},"641598":{"name":"Mitch Garver","xwoba":0.3,"pa":56,"type":"batter"},"664034":{"name":"Ty France","xwoba":0.403,"pa":56,"type":"batter"},"543309":{"name":"Kyle Higashioka","xwoba":0.299,"pa":56,"type":"batter"},"667472":{"name":"Dane Myers","xwoba":0.45,"pa":56,"type":"batter"},"664954":{"name":"Brett Sullivan","xwoba":0.269,"pa":56,"type":"batter"},"682877":{"name":"Juan Brito","xwoba":0.257,"pa":56,"type":"batter"},"664770":{"name":"Nathan Lukes","xwoba":0.281,"pa":56,"type":"batter"},"664056":{"name":"Harrison Bader","xwoba":0.261,"pa":55,"type":"batter"},"641933":{"name":"Tyler O'Neill","xwoba":0.31,"pa":55,"type":"batter"},"665561":{"name":"Rafael March\u00e1n","xwoba":0.186,"pa":54,"type":"batter"},"678218":{"name":"Brandon Valenzuela","xwoba":0.276,"pa":54,"type":"batter"},"663368":{"name":"Blake Perkins","xwoba":0.218,"pa":53,"type":"batter"},"694374":{"name":"Tim Tawa","xwoba":0.27,"pa":53,"type":"batter"},"457705":{"name":"Andrew McCutchen","xwoba":0.248,"pa":52,"type":"batter"},"687957":{"name":"Dustin Harris","xwoba":0.335,"pa":52,"type":"batter"},"543510":{"name":"James McCann","xwoba":0.628,"pa":23,"type":"pitcher"},"681807":{"name":"David Fry","xwoba":0.307,"pa":52,"type":"batter"},"657136":{"name":"Connor Wong","xwoba":0.27,"pa":51,"type":"batter"},"656716":{"name":"Zach McKinstry","xwoba":0.231,"pa":50,"type":"batter"},"622761":{"name":"Jorge Mateo","xwoba":0.274,"pa":50,"type":"batter"},"663698":{"name":"Joey Bart","xwoba":0.225,"pa":50,"type":"batter"},"666971":{"name":"Lourdes Gurriel Jr.","xwoba":0.307,"pa":50,"type":"batter"},"502671":{"name":"Paul Goldschmidt","xwoba":0.392,"pa":49,"type":"batter"},"624641":{"name":"Edmundo Sosa","xwoba":0.349,"pa":49,"type":"batter"},"680869":{"name":"Zack Gelof","xwoba":0.326,"pa":48,"type":"batter"},"608701":{"name":"Rob Refsnyder","xwoba":0.292,"pa":48,"type":"batter"},"656537":{"name":"Derek Hill","xwoba":0.327,"pa":48,"type":"batter"},"595978":{"name":"Austin Hedges","xwoba":0.482,"pa":1,"type":"pitcher"},"665161":{"name":"Jeremy Pe\u00f1a","xwoba":0.361,"pa":46,"type":"batter"},"668723":{"name":"Ryan Vilade","xwoba":0.295,"pa":46,"type":"batter"},"641680":{"name":"Jonah Heim","xwoba":0.278,"pa":45,"type":"batter"},"669720":{"name":"Austin Hays","xwoba":0.283,"pa":44,"type":"batter"},"701678":{"name":"Hao-Yu Lee","xwoba":0.286,"pa":44,"type":"batter"},"676439":{"name":"Hunter Feduccia","xwoba":0.293,"pa":44,"type":"batter"},"642851":{"name":"Austin Wynns","xwoba":0.285,"pa":43,"type":"batter"},"663330":{"name":"Jahmai Jones","xwoba":0.383,"pa":43,"type":"batter"},"676694":{"name":"Jake Meyers","xwoba":0.34,"pa":43,"type":"batter"},"669004":{"name":"MJ Melendez","xwoba":0.267,"pa":42,"type":"batter"},"643396":{"name":"Isiah Kiner-Falefa","xwoba":0.274,"pa":42,"type":"batter"},"679845":{"name":"Nick Loftin","xwoba":0.324,"pa":41,"type":"batter"},"669743":{"name":"Alex Call","xwoba":0.347,"pa":40,"type":"batter"},"624424":{"name":"Michael Conforto","xwoba":0.403,"pa":40,"type":"batter"},"678009":{"name":"Parker Meadows","xwoba":0.251,"pa":39,"type":"batter"},"665877":{"name":"Jos\u00e9 Ferm\u00edn","xwoba":0.264,"pa":38,"type":"batter"},"518595":{"name":"Travis d'Arnaud","xwoba":0.303,"pa":38,"type":"batter"},"671655":{"name":"George Valera","xwoba":0.199,"pa":38,"type":"batter"},"620443":{"name":"Luis Torrens","xwoba":0.268,"pa":38,"type":"batter"},"596103":{"name":"Austin Slater","xwoba":0.24,"pa":37,"type":"batter"},"668670":{"name":"Jake Rogers","xwoba":0.403,"pa":5,"type":"pitcher"},"641555":{"name":"J.C. Escarra","xwoba":0.278,"pa":36,"type":"batter"},"669326":{"name":"Bryce Teodosio","xwoba":0.213,"pa":36,"type":"batter"},"677956":{"name":"Rece Hinds","xwoba":0.162,"pa":36,"type":"batter"},"545341":{"name":"Randal Grichuk","xwoba":0.338,"pa":36,"type":"batter"},"650391":{"name":"Eloy Jim\u00e9nez","xwoba":0.257,"pa":35,"type":"batter"},"516782":{"name":"Starling Marte","xwoba":0.276,"pa":35,"type":"batter"},"666464":{"name":"Jerar Encarnacion","xwoba":0.21,"pa":35,"type":"batter"},"624512":{"name":"Reese McGuire","xwoba":0.027,"pa":3,"type":"pitcher"},"681546":{"name":"James Outman","xwoba":0.187,"pa":33,"type":"batter"},"666211":{"name":"Taylor Trammell","xwoba":0.291,"pa":33,"type":"batter"},"695020":{"name":"Tanner Murray","xwoba":0.276,"pa":33,"type":"batter"},"672356":{"name":"Gabriel Arias","xwoba":0.293,"pa":32,"type":"batter"},"605141":{"name":"Mookie Betts","xwoba":0.332,"pa":32,"type":"batter"},"677595":{"name":"Ronny Mauricio","xwoba":0.224,"pa":32,"type":"batter"},"682622":{"name":"Noelvi Marte","xwoba":0.161,"pa":31,"type":"batter"},"664059":{"name":"Sam Haggerty","xwoba":0.178,"pa":30,"type":"batter"},"669707":{"name":"Jared Triolo","xwoba":0.279,"pa":30,"type":"batter"},"668709":{"name":"JJ Bleday","xwoba":0.519,"pa":29,"type":"batter"},"683953":{"name":"Travis Bazzana","xwoba":0.352,"pa":29,"type":"batter"},"669289":{"name":"Santiago Espinal","xwoba":0.28,"pa":28,"type":"batter"},"691176":{"name":"Jasson Dom\u00ednguez","xwoba":0.334,"pa":28,"type":"batter"},"694025":{"name":"Felix Reyes","xwoba":0.213,"pa":28,"type":"batter"},"669369":{"name":"Bryce Johnson","xwoba":0.159,"pa":27,"type":"batter"},"467793":{"name":"Carlos Santana","xwoba":0.188,"pa":26,"type":"batter"},"692216":{"name":"CJ Kayfus","xwoba":0.305,"pa":25,"type":"batter"},"665052":{"name":"Griffin Conine","xwoba":0.513,"pa":25,"type":"batter"},"700246":{"name":"Carson Williams","xwoba":0.19,"pa":25,"type":"batter"},"669397":{"name":"Nick Allen","xwoba":0.29,"pa":25,"type":"batter"},"691740":{"name":"Daniel Susac","xwoba":0.387,"pa":24,"type":"batter"},"696030":{"name":"Alejandro Osuna","xwoba":0.349,"pa":24,"type":"batter"},"676724":{"name":"Jared Young","xwoba":0.364,"pa":23,"type":"batter"},"682818":{"name":"Yohendrick Pi\u00f1ango","xwoba":0.363,"pa":23,"type":"batter"},"680718":{"name":"Addison Barger","xwoba":0.231,"pa":23,"type":"batter"},"672012":{"name":"Tyler Black","xwoba":0.184,"pa":23,"type":"batter"},"687515":{"name":"Colby Thomas","xwoba":0.309,"pa":22,"type":"batter"},"675659":{"name":"Greg Jones","xwoba":0.175,"pa":22,"type":"batter"},"805249":{"name":"Otto Kemp","xwoba":0.229,"pa":22,"type":"batter"},"656582":{"name":"Connor Joe","xwoba":0.367,"pa":22,"type":"batter"},"672386":{"name":"Alejandro Kirk","xwoba":0.299,"pa":22,"type":"batter"},"642215":{"name":"Weston Wilson","xwoba":0.553,"pa":9,"type":"pitcher"},"691011":{"name":"Drew Romo","xwoba":0.503,"pa":21,"type":"batter"},"628451":{"name":"Andy Ib\u00e1\u00f1ez","xwoba":0.185,"pa":21,"type":"batter"},"677870":{"name":"Leo Jim\u00e9nez","xwoba":0.317,"pa":21,"type":"batter"},"682641":{"name":"Luis Matos","xwoba":0.13,"pa":21,"type":"batter"},"691783":{"name":"Jordan Lawlar","xwoba":0.361,"pa":20,"type":"batter"},"624431":{"name":"Jose Trevino","xwoba":0.453,"pa":24,"type":"pitcher"},"600869":{"name":"Jeimer Candelario","xwoba":0.219,"pa":20,"type":"batter"},"668952":{"name":"Ryan Kreidler","xwoba":0.48,"pa":18,"type":"batter"},"596117":{"name":"Garrett Stubbs","xwoba":0.268,"pa":17,"type":"batter"},"650968":{"name":"Yohel Pozo","xwoba":0.247,"pa":17,"type":"batter"},"669288":{"name":"Daniel Johnson","xwoba":0.343,"pa":17,"type":"batter"},"666624":{"name":"Christopher Morel","xwoba":0.298,"pa":16,"type":"batter"},"672284":{"name":"Jarred Kelenic","xwoba":0.428,"pa":15,"type":"batter"},"663624":{"name":"Ryan Mountcastle","xwoba":0.301,"pa":15,"type":"batter"},"665923":{"name":"Esteury Ruiz","xwoba":0.311,"pa":15,"type":"batter"},"664238":{"name":"Dylan Moore","xwoba":0.381,"pa":8,"type":"pitcher"},"502054":{"name":"Tommy Pham","xwoba":0.138,"pa":14,"type":"batter"},"694376":{"name":"Shay Whitcomb","xwoba":0.181,"pa":14,"type":"batter"},"669699":{"name":"Braden Shewmake","xwoba":0.237,"pa":14,"type":"batter"},"695257":{"name":"Billy Cook","xwoba":0.199,"pa":13,"type":"batter"},"645302":{"name":"Victor Robles","xwoba":0.256,"pa":13,"type":"batter"},"683766":{"name":"Christian Koss","xwoba":0.245,"pa":3,"type":"pitcher"},"571657":{"name":"Kyle Farmer","xwoba":0.285,"pa":13,"type":"batter"},"664731":{"name":"P.J. Higgins","xwoba":0.034,"pa":3,"type":"pitcher"},"553869":{"name":"Elias D\u00edaz","xwoba":0.375,"pa":12,"type":"batter"},"671286":{"name":"Johnathan Rodr\u00edguez","xwoba":0.332,"pa":11,"type":"batter"},"665953":{"name":"Andr\u00e9s Chaparro","xwoba":0.489,"pa":10,"type":"batter"},"606992":{"name":"Eric Haase","xwoba":0.296,"pa":10,"type":"batter"},"683734":{"name":"Andrew Vaughn","xwoba":0.219,"pa":9,"type":"batter"},"665861":{"name":"Sebasti\u00e1n Rivero","xwoba":0.284,"pa":9,"type":"batter"},"686823":{"name":"Will Brennan","xwoba":0.058,"pa":9,"type":"batter"},"669087":{"name":"Sam Huff","xwoba":0.132,"pa":9,"type":"batter"},"656976":{"name":"Pavin Smith","xwoba":0.263,"pa":8,"type":"batter"},"805904":{"name":"Zach Cole","xwoba":0.343,"pa":7,"type":"batter"},"666931":{"name":"Jared Oliva","xwoba":0.308,"pa":7,"type":"batter"},"805811":{"name":"Bryce Eldridge","xwoba":0.295,"pa":7,"type":"batter"},"691788":{"name":"Joe Mack","xwoba":0.23,"pa":7,"type":"batter"},"690022":{"name":"Ryan Ritter","xwoba":0.166,"pa":7,"type":"batter"},"691277":{"name":"Deyvison De Los Santos","xwoba":0.221,"pa":7,"type":"batter"},"683679":{"name":"Jesus Rodriguez","xwoba":0.319,"pa":6,"type":"batter"},"669717":{"name":"Will Wilson","xwoba":0.453,"pa":6,"type":"batter"},"690291":{"name":"Jace Jung","xwoba":0.411,"pa":6,"type":"batter"},"669899":{"name":"Ryan Ward","xwoba":0.299,"pa":6,"type":"batter"},"663609":{"name":"Luken Baker","xwoba":0.123,"pa":5,"type":"batter"},"694192":{"name":"Jackson Chourio","xwoba":1.09,"pa":5,"type":"batter"},"686475":{"name":"Tyler Tolbert","xwoba":0.297,"pa":2,"type":"pitcher"},"690924":{"name":"Braxton Fulford","xwoba":0.115,"pa":5,"type":"batter"},"690984":{"name":"Petey Halpin","xwoba":0.115,"pa":5,"type":"batter"},"695391":{"name":"Brett Harris","xwoba":0.305,"pa":5,"type":"batter"},"823550":{"name":"Sung-Mun Song","xwoba":0.28,"pa":4,"type":"batter"},"664068":{"name":"Scott Kingery","xwoba":0.156,"pa":4,"type":"batter"},"666185":{"name":"Dylan Carlson","xwoba":0.07,"pa":4,"type":"batter"},"670032":{"name":"Nicky Lopez","xwoba":0.161,"pa":4,"type":"batter"},"605244":{"name":"Aramis Garcia","xwoba":0.308,"pa":3,"type":"batter"},"640902":{"name":"Jhonny Pereda","xwoba":0.11,"pa":3,"type":"batter"},"669221":{"name":"Sean Murphy","xwoba":0.181,"pa":3,"type":"batter"},"670097":{"name":"Zack Short","xwoba":0.242,"pa":3,"type":"batter"},"691620":{"name":"Jeferson Quero","xwoba":0.499,"pa":2,"type":"batter"},"680474":{"name":"Max Schuemann","xwoba":0.354,"pa":2,"type":"batter"},"640492":{"name":"Jos\u00e9 Azocar","xwoba":0.223,"pa":2,"type":"batter"},"679822":{"name":"Justin Foscue","xwoba":0.042,"pa":1,"type":"batter"},"663897":{"name":"Luke Williams","xwoba":0.707,"pa":1,"type":"batter"},"645261":{"name":"Sandy Alcantara","xwoba":0.296,"pa":218,"type":"pitcher"},"650911":{"name":"Cristopher S\u00e1nchez","xwoba":0.281,"pa":209,"type":"pitcher"},"657277":{"name":"Logan Webb","xwoba":0.336,"pa":208,"type":"pitcher"},"669923":{"name":"George Kirby","xwoba":0.267,"pa":204,"type":"pitcher"},"608331":{"name":"Max Fried","xwoba":0.244,"pa":201,"type":"pitcher"},"671737":{"name":"Taj Bradley","xwoba":0.312,"pa":199,"type":"pitcher"},"668909":{"name":"Gavin Williams","xwoba":0.326,"pa":198,"type":"pitcher"},"664285":{"name":"Framber Valdez","xwoba":0.328,"pa":195,"type":"pitcher"},"693821":{"name":"Bryce Elder","xwoba":0.269,"pa":195,"type":"pitcher"},"622663":{"name":"Luis Severino","xwoba":0.333,"pa":186,"type":"pitcher"},"667755":{"name":"Jos\u00e9 Soriano","xwoba":0.312,"pa":186,"type":"pitcher"},"669302":{"name":"Logan Gilbert","xwoba":0.343,"pa":185,"type":"pitcher"},"592332":{"name":"Kevin Gausman","xwoba":0.293,"pa":185,"type":"pitcher"},"671096":{"name":"Andrew Abbott","xwoba":0.36,"pa":182,"type":"pitcher"},"693645":{"name":"Cam Schlittler","xwoba":0.263,"pa":181,"type":"pitcher"},"669358":{"name":"Shane Baz","xwoba":0.34,"pa":176,"type":"pitcher"},"686799":{"name":"Jack Kochanowicz","xwoba":0.333,"pa":175,"type":"pitcher"},"608379":{"name":"Michael Wacha","xwoba":0.327,"pa":174,"type":"pitcher"},"607625":{"name":"Seth Lugo","xwoba":0.32,"pa":174,"type":"pitcher"},"543135":{"name":"Nathan Eovaldi","xwoba":0.33,"pa":173,"type":"pitcher"},"676440":{"name":"Tanner Bibee","xwoba":0.321,"pa":172,"type":"pitcher"},"666200":{"name":"Jes\u00fas Luzardo","xwoba":0.284,"pa":172,"type":"pitcher"},"665795":{"name":"Edward Cabrera","xwoba":0.324,"pa":171,"type":"pitcher"},"808967":{"name":"Yoshinobu Yamamoto","xwoba":0.325,"pa":170,"type":"pitcher"},"663436":{"name":"Davis Martin","xwoba":0.324,"pa":169,"type":"pitcher"},"593958":{"name":"Eduardo Rodriguez","xwoba":0.341,"pa":169,"type":"pitcher"},"681347":{"name":"Mike Burrows","xwoba":0.311,"pa":169,"type":"pitcher"},"672282":{"name":"Reid Detmers","xwoba":0.269,"pa":168,"type":"pitcher"},"607259":{"name":"Nick Martinez","xwoba":0.313,"pa":168,"type":"pitcher"},"605280":{"name":"Clay Holmes","xwoba":0.309,"pa":168,"type":"pitcher"},"656302":{"name":"Dylan Cease","xwoba":0.278,"pa":166,"type":"pitcher"},"693433":{"name":"Bryan Woo","xwoba":0.319,"pa":166,"type":"pitcher"},"669373":{"name":"Tarik Skubal","xwoba":0.284,"pa":166,"type":"pitcher"},"677952":{"name":"Braxton Ashcraft","xwoba":0.26,"pa":165,"type":"pitcher"},"676917":{"name":"Cade Cavalli","xwoba":0.309,"pa":165,"type":"pitcher"},"519242":{"name":"Chris Sale","xwoba":0.27,"pa":164,"type":"pitcher"},"683004":{"name":"Jack Leiter","xwoba":0.346,"pa":164,"type":"pitcher"},"642547":{"name":"Freddy Peralta","xwoba":0.305,"pa":164,"type":"pitcher"},"592791":{"name":"Jameson Taillon","xwoba":0.315,"pa":164,"type":"pitcher"},"547179":{"name":"Michael Lorenzen","xwoba":0.366,"pa":164,"type":"pitcher"},"677944":{"name":"Slade Cecconi","xwoba":0.368,"pa":164,"type":"pitcher"},"656605":{"name":"Mitch Keller","xwoba":0.308,"pa":163,"type":"pitcher"},"656492":{"name":"Foster Griffin","xwoba":0.331,"pa":163,"type":"pitcher"},"663460":{"name":"Kris Bubic","xwoba":0.311,"pa":163,"type":"pitcher"},"680573":{"name":"Simeon Woods Richardson","xwoba":0.356,"pa":161,"type":"pitcher"},"695505":{"name":"Chase Burns","xwoba":0.276,"pa":161,"type":"pitcher"},"681190":{"name":"Randy V\u00e1squez","xwoba":0.335,"pa":161,"type":"pitcher"},"605400":{"name":"Aaron Nola","xwoba":0.331,"pa":161,"type":"pitcher"},"656550":{"name":"Grant Holmes","xwoba":0.329,"pa":160,"type":"pitcher"},"622491":{"name":"Luis Castillo","xwoba":0.374,"pa":160,"type":"pitcher"},"650633":{"name":"Michael King","xwoba":0.317,"pa":159,"type":"pitcher"},"656849":{"name":"David Peterson","xwoba":0.342,"pa":159,"type":"pitcher"},"684007":{"name":"Shota Imanaga","xwoba":0.269,"pa":159,"type":"pitcher"},"694738":{"name":"Landen Roupp","xwoba":0.26,"pa":159,"type":"pitcher"},"681517":{"name":"Kyle Leahy","xwoba":0.378,"pa":159,"type":"pitcher"},"676106":{"name":"Emerson Hancock","xwoba":0.303,"pa":159,"type":"pitcher"},"650644":{"name":"Aaron Civale","xwoba":0.324,"pa":158,"type":"pitcher"},"669461":{"name":"Matthew Liberatore","xwoba":0.373,"pa":158,"type":"pitcher"},"691587":{"name":"Eury P\u00e9rez","xwoba":0.35,"pa":158,"type":"pitcher"},"677960":{"name":"Ryan Weathers","xwoba":0.34,"pa":158,"type":"pitcher"},"605488":{"name":"Jeffrey Springs","xwoba":0.285,"pa":158,"type":"pitcher"},"641816":{"name":"Tyler Mahle","xwoba":0.34,"pa":158,"type":"pitcher"},"678394":{"name":"Brayan Bello","xwoba":0.401,"pa":158,"type":"pitcher"},"657746":{"name":"Joe Ryan","xwoba":0.282,"pa":157,"type":"pitcher"},"641927":{"name":"Bailey Ober","xwoba":0.31,"pa":157,"type":"pitcher"},"592662":{"name":"Robbie Ray","xwoba":0.314,"pa":157,"type":"pitcher"},"680694":{"name":"Kyle Bradish","xwoba":0.353,"pa":157,"type":"pitcher"},"680732":{"name":"Sean Burke","xwoba":0.293,"pa":156,"type":"pitcher"},"605135":{"name":"Chris Bassitt","xwoba":0.365,"pa":156,"type":"pitcher"},"801403":{"name":"Chase Dollander","xwoba":0.283,"pa":156,"type":"pitcher"},"800048":{"name":"Parker Messick","xwoba":0.27,"pa":156,"type":"pitcher"},"669160":{"name":"Dustin May","xwoba":0.323,"pa":155,"type":"pitcher"},"676083":{"name":"Janson Junk","xwoba":0.29,"pa":155,"type":"pitcher"},"694819":{"name":"Jacob Misiorowski","xwoba":0.272,"pa":155,"type":"pitcher"},"607200":{"name":"Erick Fedde","xwoba":0.319,"pa":155,"type":"pitcher"},"663623":{"name":"Jake Irvin","xwoba":0.344,"pa":154,"type":"pitcher"},"669387":{"name":"Carmen Mlodzinski","xwoba":0.331,"pa":154,"type":"pitcher"},"676974":{"name":"Max Meyer","xwoba":0.313,"pa":154,"type":"pitcher"},"663903":{"name":"Brady Singer","xwoba":0.382,"pa":153,"type":"pitcher"},"690997":{"name":"Nolan McLean","xwoba":0.244,"pa":153,"type":"pitcher"},"695076":{"name":"Rhett Lowder","xwoba":0.339,"pa":153,"type":"pitcher"},"701542":{"name":"Will Warren","xwoba":0.293,"pa":152,"type":"pitcher"},"696149":{"name":"Bubba Chandler","xwoba":0.354,"pa":152,"type":"pitcher"},"608372":{"name":"Tomoyuki Sugano","xwoba":0.383,"pa":151,"type":"pitcher"},"669022":{"name":"MacKenzie Gore","xwoba":0.327,"pa":151,"type":"pitcher"},"813349":{"name":"Connelly Early","xwoba":0.36,"pa":151,"type":"pitcher"},"594798":{"name":"Jacob deGrom","xwoba":0.296,"pa":150,"type":"pitcher"},"641793":{"name":"Zack Littell","xwoba":0.431,"pa":150,"type":"pitcher"},"571927":{"name":"Steven Matz","xwoba":0.342,"pa":149,"type":"pitcher"},"624133":{"name":"Ranger Suarez","xwoba":0.296,"pa":148,"type":"pitcher"},"656876":{"name":"Drew Rasmussen","xwoba":0.285,"pa":147,"type":"pitcher"},"700241":{"name":"Michael McGreevy","xwoba":0.372,"pa":147,"type":"pitcher"},"682052":{"name":"Jacob Lopez","xwoba":0.296,"pa":146,"type":"pitcher"},"663978":{"name":"Chris Paddack","xwoba":0.329,"pa":146,"type":"pitcher"},"676282":{"name":"Joey Cantillo","xwoba":0.325,"pa":145,"type":"pitcher"},"702070":{"name":"Noah Cameron","xwoba":0.386,"pa":144,"type":"pitcher"},"607192":{"name":"Tyler Glasnow","xwoba":0.248,"pa":144,"type":"pitcher"},"605288":{"name":"Adrian Houser","xwoba":0.377,"pa":143,"type":"pitcher"},"641743":{"name":"Anthony Kay","xwoba":0.416,"pa":143,"type":"pitcher"},"669194":{"name":"Ryne Nelson","xwoba":0.372,"pa":143,"type":"pitcher"},"680736":{"name":"Justin Wrobleski","xwoba":0.325,"pa":143,"type":"pitcher"},"607067":{"name":"Colin Rea","xwoba":0.331,"pa":142,"type":"pitcher"},"579328":{"name":"Yusei Kikuchi","xwoba":0.341,"pa":142,"type":"pitcher"},"668678":{"name":"Zac Gallen","xwoba":0.356,"pa":141,"type":"pitcher"},"641778":{"name":"Eric Lauer","xwoba":0.362,"pa":141,"type":"pitcher"},"656427":{"name":"Jack Flaherty","xwoba":0.36,"pa":141,"type":"pitcher"},"669467":{"name":"Andre Pallante","xwoba":0.331,"pa":138,"type":"pitcher"},"676979":{"name":"Garrett Crochet","xwoba":0.345,"pa":138,"type":"pitcher"},"666142":{"name":"Cole Ragans","xwoba":0.358,"pa":138,"type":"pitcher"},"621111":{"name":"Walker Buehler","xwoba":0.341,"pa":137,"type":"pitcher"},"647336":{"name":"Michael Soroka","xwoba":0.353,"pa":136,"type":"pitcher"},"808963":{"name":"Roki Sasaki","xwoba":0.372,"pa":134,"type":"pitcher"},"694477":{"name":"Chad Patrick","xwoba":0.337,"pa":134,"type":"pitcher"},"621121":{"name":"Lance McCullers Jr.","xwoba":0.33,"pa":133,"type":"pitcher"},"691725":{"name":"Andrew Painter","xwoba":0.318,"pa":133,"type":"pitcher"},"672456":{"name":"Keider Montero","xwoba":0.282,"pa":133,"type":"pitcher"},"669432":{"name":"Trevor Rogers","xwoba":0.305,"pa":133,"type":"pitcher"},"694973":{"name":"Paul Skenes","xwoba":0.24,"pa":133,"type":"pitcher"},"686218":{"name":"Emmet Sheehan","xwoba":0.328,"pa":132,"type":"pitcher"},"680802":{"name":"Ryan Weiss","xwoba":0.381,"pa":131,"type":"pitcher"},"694297":{"name":"Brandon Pfaadt","xwoba":0.343,"pa":128,"type":"pitcher"},"663554":{"name":"Casey Mize","xwoba":0.295,"pa":128,"type":"pitcher"},"608566":{"name":"Germ\u00e1n M\u00e1rquez","xwoba":0.368,"pa":128,"type":"pitcher"},"682227":{"name":"Brandon Williamson","xwoba":0.39,"pa":128,"type":"pitcher"},"677958":{"name":"Kumar Rocker","xwoba":0.345,"pa":127,"type":"pitcher"},"571945":{"name":"Miles Mikolas","xwoba":0.356,"pa":127,"type":"pitcher"},"669372":{"name":"J.T. Ginn","xwoba":0.308,"pa":123,"type":"pitcher"},"663556":{"name":"Shane McClanahan","xwoba":0.311,"pa":121,"type":"pitcher"},"605540":{"name":"Brandon Woodruff","xwoba":0.28,"pa":121,"type":"pitcher"},"690986":{"name":"Kyle Harrison","xwoba":0.292,"pa":120,"type":"pitcher"},"592836":{"name":"Taijuan Walker","xwoba":0.405,"pa":115,"type":"pitcher"},"687075":{"name":"Brandon Sproat","xwoba":0.358,"pa":115,"type":"pitcher"},"527048":{"name":"Mart\u00edn P\u00e9rez","xwoba":0.333,"pa":112,"type":"pitcher"},"607536":{"name":"Kyle Freeland","xwoba":0.337,"pa":111,"type":"pitcher"},"625643":{"name":"Reynaldo L\u00f3pez","xwoba":0.336,"pa":106,"type":"pitcher"},"500779":{"name":"Jose Quintana","xwoba":0.359,"pa":105,"type":"pitcher"},"640455":{"name":"Sean Manaea","xwoba":0.359,"pa":103,"type":"pitcher"},"571578":{"name":"Patrick Corbin","xwoba":0.37,"pa":102,"type":"pitcher"},"695418":{"name":"Brad Lord","xwoba":0.319,"pa":102,"type":"pitcher"},"676962":{"name":"Ben Brown","xwoba":0.267,"pa":101,"type":"pitcher"},"681293":{"name":"Spencer Arrighetti","xwoba":0.371,"pa":101,"type":"pitcher"},"571510":{"name":"Matthew Boyd","xwoba":0.322,"pa":100,"type":"pitcher"},"543243":{"name":"Sonny Gray","xwoba":0.369,"pa":99,"type":"pitcher"},"518876":{"name":"Merrill Kelly","xwoba":0.487,"pa":98,"type":"pitcher"},"805123":{"name":"AJ Blubaugh","xwoba":0.334,"pa":97,"type":"pitcher"},"673540":{"name":"Kodai Senga","xwoba":0.339,"pa":97,"type":"pitcher"},"670245":{"name":"Ryan Watson","xwoba":0.4,"pa":96,"type":"pitcher"},"670990":{"name":"Yohan Ram\u00edrez","xwoba":0.283,"pa":95,"type":"pitcher"},"669947":{"name":"Jesse Scholtens","xwoba":0.321,"pa":94,"type":"pitcher"},"663567":{"name":"Peter Lambert","xwoba":0.291,"pa":93,"type":"pitcher"},"663969":{"name":"Tyler Phillips","xwoba":0.318,"pa":93,"type":"pitcher"},"690953":{"name":"Mick Abel","xwoba":0.351,"pa":93,"type":"pitcher"},"676879":{"name":"Aaron Ashby","xwoba":0.26,"pa":92,"type":"pitcher"},"678906":{"name":"Kai-Wei Teng","xwoba":0.289,"pa":89,"type":"pitcher"},"683175":{"name":"Connor Phillips","xwoba":0.369,"pa":89,"type":"pitcher"},"694335":{"name":"Matt Svanson","xwoba":0.418,"pa":88,"type":"pitcher"},"665871":{"name":"Javier Assad","xwoba":0.349,"pa":88,"type":"pitcher"},"663372":{"name":"Ryan Feltner","xwoba":0.39,"pa":88,"type":"pitcher"},"663687":{"name":"Hogan Harris","xwoba":0.31,"pa":88,"type":"pitcher"},"663558":{"name":"Jovani Mor\u00e1n","xwoba":0.297,"pa":87,"type":"pitcher"},"688642":{"name":"Zach Agnos","xwoba":0.337,"pa":86,"type":"pitcher"},"656794":{"name":"Sean Newcomb","xwoba":0.281,"pa":86,"type":"pitcher"},"642121":{"name":"Cole Sulser","xwoba":0.328,"pa":85,"type":"pitcher"},"702273":{"name":"Noah Schultz","xwoba":0.293,"pa":85,"type":"pitcher"},"661563":{"name":"Luis Gil","xwoba":0.386,"pa":85,"type":"pitcher"},"623454":{"name":"Drew Anderson","xwoba":0.318,"pa":84,"type":"pitcher"},"453286":{"name":"Max Scherzer","xwoba":0.397,"pa":84,"type":"pitcher"},"608718":{"name":"Brent Suter","xwoba":0.302,"pa":84,"type":"pitcher"},"676760":{"name":"Ron Marinaccio","xwoba":0.316,"pa":83,"type":"pitcher"},"666171":{"name":"Ryan Zeferjahn","xwoba":0.234,"pa":83,"type":"pitcher"},"668964":{"name":"Tobias Myers","xwoba":0.26,"pa":83,"type":"pitcher"},"622608":{"name":"Antonio Senzatela","xwoba":0.268,"pa":82,"type":"pitcher"},"672782":{"name":"Yoendrys G\u00f3mez","xwoba":0.413,"pa":82,"type":"pitcher"},"678606":{"name":"Jose A. Ferrer","xwoba":0.239,"pa":81,"type":"pitcher"},"670970":{"name":"Adrian Morejon","xwoba":0.292,"pa":79,"type":"pitcher"},"700712":{"name":"Walbert Ure\u00f1a","xwoba":0.294,"pa":79,"type":"pitcher"},"660761":{"name":"Jos\u00e9 Suarez","xwoba":0.316,"pa":79,"type":"pitcher"},"686993":{"name":"Justin Sterner","xwoba":0.264,"pa":79,"type":"pitcher"},"675848":{"name":"Juan Mejia","xwoba":0.304,"pa":78,"type":"pitcher"},"677865":{"name":"Justin Bruihl","xwoba":0.385,"pa":78,"type":"pitcher"},"687396":{"name":"Brent Headrick","xwoba":0.285,"pa":77,"type":"pitcher"},"656546":{"name":"Jeff Hoffman","xwoba":0.279,"pa":77,"type":"pitcher"},"592773":{"name":"Ryne Stanek","xwoba":0.324,"pa":76,"type":"pitcher"},"669330":{"name":"Tyler Wells","xwoba":0.302,"pa":76,"type":"pitcher"},"693686":{"name":"Spencer Miles","xwoba":0.301,"pa":75,"type":"pitcher"},"641835":{"name":"Tim Mayza","xwoba":0.271,"pa":75,"type":"pitcher"},"702275":{"name":"JR Ritchie","xwoba":0.354,"pa":75,"type":"pitcher"},"696147":{"name":"Sam Bachman","xwoba":0.263,"pa":75,"type":"pitcher"},"664141":{"name":"JT Brubaker","xwoba":0.371,"pa":74,"type":"pitcher"},"676571":{"name":"PJ Poulin","xwoba":0.354,"pa":74,"type":"pitcher"},"689296":{"name":"Anthony Nunez","xwoba":0.337,"pa":73,"type":"pitcher"},"672335":{"name":"Cionel P\u00e9rez","xwoba":0.446,"pa":73,"type":"pitcher"},"641302":{"name":"Tyler Alexander","xwoba":0.284,"pa":73,"type":"pitcher"},"641312":{"name":"Shaun Anderson","xwoba":0.37,"pa":73,"type":"pitcher"},"663765":{"name":"Jake Woodford","xwoba":0.361,"pa":73,"type":"pitcher"},"693855":{"name":"Ian Seymour","xwoba":0.329,"pa":73,"type":"pitcher"},"691799":{"name":"Grant Taylor","xwoba":0.26,"pa":73,"type":"pitcher"},"679358":{"name":"Eric Orze","xwoba":0.285,"pa":72,"type":"pitcher"},"670036":{"name":"Matt Festa","xwoba":0.28,"pa":72,"type":"pitcher"},"656271":{"name":"Brock Burke","xwoba":0.334,"pa":72,"type":"pitcher"},"663542":{"name":"Bryan Hudson","xwoba":0.269,"pa":72,"type":"pitcher"},"674370":{"name":"Osvaldo Bido","xwoba":0.377,"pa":72,"type":"pitcher"},"676755":{"name":"Isaac Mattson","xwoba":0.39,"pa":72,"type":"pitcher"},"668941":{"name":"JoJo Romero","xwoba":0.376,"pa":71,"type":"pitcher"},"643410":{"name":"Mark Leiter Jr.","xwoba":0.373,"pa":71,"type":"pitcher"},"700669":{"name":"Gordon Graceffo","xwoba":0.394,"pa":71,"type":"pitcher"},"668933":{"name":"Graham Ashcraft","xwoba":0.284,"pa":71,"type":"pitcher"},"670280":{"name":"David Bednar","xwoba":0.256,"pa":71,"type":"pitcher"},"668984":{"name":"Casey Legumina","xwoba":0.357,"pa":70,"type":"pitcher"},"607455":{"name":"Anthony Banda","xwoba":0.318,"pa":70,"type":"pitcher"},"663947":{"name":"Tyler Holton","xwoba":0.373,"pa":70,"type":"pitcher"},"669199":{"name":"Lake Bachar","xwoba":0.237,"pa":70,"type":"pitcher"},"621383":{"name":"Tanner Banks","xwoba":0.324,"pa":70,"type":"pitcher"},"677961":{"name":"Cole Wilcox","xwoba":0.409,"pa":70,"type":"pitcher"},"680755":{"name":"Braydon Fisher","xwoba":0.319,"pa":70,"type":"pitcher"},"593974":{"name":"Wandy Peralta","xwoba":0.327,"pa":69,"type":"pitcher"},"663362":{"name":"Matt Waldron","xwoba":0.338,"pa":69,"type":"pitcher"},"687911":{"name":"Bryan King","xwoba":0.276,"pa":69,"type":"pitcher"},"687064":{"name":"Brandon Young","xwoba":0.372,"pa":68,"type":"pitcher"},"673929":{"name":"Jordan Leasure","xwoba":0.39,"pa":68,"type":"pitcher"},"606996":{"name":"Kyle Hart","xwoba":0.303,"pa":68,"type":"pitcher"},"700249":{"name":"Cade Povich","xwoba":0.348,"pa":68,"type":"pitcher"},"605130":{"name":"Scott Barlow","xwoba":0.301,"pa":68,"type":"pitcher"},"676428":{"name":"Brant Hurter","xwoba":0.294,"pa":68,"type":"pitcher"},"688158":{"name":"David Morgan","xwoba":0.305,"pa":68,"type":"pitcher"},"688883":{"name":"Peyton Pallette","xwoba":0.362,"pa":67,"type":"pitcher"},"641755":{"name":"Tyler Kinley","xwoba":0.273,"pa":67,"type":"pitcher"},"667297":{"name":"Tommy Nance","xwoba":0.298,"pa":67,"type":"pitcher"},"669084":{"name":"DL Hall","xwoba":0.311,"pa":67,"type":"pitcher"},"801139":{"name":"Payton Tolle","xwoba":0.228,"pa":67,"type":"pitcher"},"686973":{"name":"Louis Varland","xwoba":0.196,"pa":67,"type":"pitcher"},"656638":{"name":"Alex Lange","xwoba":0.35,"pa":67,"type":"pitcher"},"642701":{"name":"Dennis Santana","xwoba":0.363,"pa":67,"type":"pitcher"},"623437":{"name":"Justin Topa","xwoba":0.374,"pa":67,"type":"pitcher"},"643511":{"name":"Tyler Rogers","xwoba":0.21,"pa":67,"type":"pitcher"},"699134":{"name":"Bradgley Rodriguez","xwoba":0.236,"pa":67,"type":"pitcher"},"676617":{"name":"Riley O'Brien","xwoba":0.232,"pa":67,"type":"pitcher"},"595345":{"name":"Steven Okert","xwoba":0.348,"pa":67,"type":"pitcher"},"680767":{"name":"Victor Vodnik","xwoba":0.34,"pa":66,"type":"pitcher"},"662253":{"name":"Andr\u00e9s Mu\u00f1oz","xwoba":0.35,"pa":66,"type":"pitcher"},"663855":{"name":"Jordan Hicks","xwoba":0.302,"pa":66,"type":"pitcher"},"544150":{"name":"Albert Su\u00e1rez","xwoba":0.348,"pa":66,"type":"pitcher"},"671212":{"name":"Joe Boyle","xwoba":0.329,"pa":66,"type":"pitcher"},"702193":{"name":"Andrew Morris","xwoba":0.285,"pa":66,"type":"pitcher"},"640448":{"name":"Kyle Finnegan","xwoba":0.278,"pa":66,"type":"pitcher"},"666277":{"name":"George Soriano","xwoba":0.324,"pa":66,"type":"pitcher"},"601713":{"name":"Nick Pivetta","xwoba":0.213,"pa":66,"type":"pitcher"},"663992":{"name":"Richard Lovelady","xwoba":0.302,"pa":65,"type":"pitcher"},"650556":{"name":"Bryan Abreu","xwoba":0.388,"pa":65,"type":"pitcher"},"571948":{"name":"Hoby Milner","xwoba":0.347,"pa":65,"type":"pitcher"},"519141":{"name":"Drew Pomeranz","xwoba":0.37,"pa":65,"type":"pitcher"},"671922":{"name":"Cade Smith","xwoba":0.304,"pa":65,"type":"pitcher"},"642528":{"name":"Jonathan Lo\u00e1isiga","xwoba":0.326,"pa":64,"type":"pitcher"},"664875":{"name":"Justin Lawrence","xwoba":0.363,"pa":64,"type":"pitcher"},"663574":{"name":"Tony Santillan","xwoba":0.357,"pa":64,"type":"pitcher"},"681982":{"name":"Grant Anderson","xwoba":0.297,"pa":64,"type":"pitcher"},"594580":{"name":"Sam Moll","xwoba":0.307,"pa":64,"type":"pitcher"},"668873":{"name":"Caleb Kilian","xwoba":0.273,"pa":64,"type":"pitcher"},"657097":{"name":"Jacob Webb","xwoba":0.389,"pa":63,"type":"pitcher"},"623211":{"name":"Huascar Brazob\u00e1n","xwoba":0.263,"pa":63,"type":"pitcher"},"573124":{"name":"Taylor Rogers","xwoba":0.378,"pa":63,"type":"pitcher"},"642397":{"name":"Gregory Soto","xwoba":0.221,"pa":63,"type":"pitcher"},"664199":{"name":"Taylor Clarke","xwoba":0.263,"pa":63,"type":"pitcher"},"643377":{"name":"Griffin Jax","xwoba":0.375,"pa":62,"type":"pitcher"},"518585":{"name":"Fernando Cruz","xwoba":0.335,"pa":62,"type":"pitcher"},"641941":{"name":"Emilio Pag\u00e1n","xwoba":0.341,"pa":62,"type":"pitcher"},"646241":{"name":"Enmanuel De Jesus","xwoba":0.346,"pa":62,"type":"pitcher"},"656464":{"name":"Kevin Ginkel","xwoba":0.263,"pa":62,"type":"pitcher"},"656641":{"name":"Jacob Latz","xwoba":0.207,"pa":62,"type":"pitcher"},"668674":{"name":"Lucas Erceg","xwoba":0.31,"pa":62,"type":"pitcher"},"669622":{"name":"Anthony Bender","xwoba":0.277,"pa":62,"type":"pitcher"},"669711":{"name":"Greg Weissert","xwoba":0.322,"pa":62,"type":"pitcher"},"676477":{"name":"Garrett Whitlock","xwoba":0.342,"pa":62,"type":"pitcher"},"677053":{"name":"Andrew Nardi","xwoba":0.401,"pa":62,"type":"pitcher"},"677955":{"name":"Jaden Hill","xwoba":0.33,"pa":62,"type":"pitcher"},"694361":{"name":"Will Klein","xwoba":0.264,"pa":62,"type":"pitcher"},"676263":{"name":"Jack Dreyer","xwoba":0.273,"pa":61,"type":"pitcher"},"669276":{"name":"Dylan Lee","xwoba":0.206,"pa":61,"type":"pitcher"},"660853":{"name":"Enyel De Los Santos","xwoba":0.29,"pa":61,"type":"pitcher"},"660825":{"name":"Eduard Bazardo","xwoba":0.275,"pa":61,"type":"pitcher"},"656222":{"name":"Jalen Beeks","xwoba":0.302,"pa":61,"type":"pitcher"},"666661":{"name":"Juan Morillo","xwoba":0.21,"pa":61,"type":"pitcher"},"685299":{"name":"Tanner Gordon","xwoba":0.343,"pa":61,"type":"pitcher"},"676254":{"name":"Ryan Walker","xwoba":0.295,"pa":61,"type":"pitcher"},"623474":{"name":"Jimmy Herget","xwoba":0.327,"pa":60,"type":"pitcher"},"622554":{"name":"Seranthony Dom\u00ednguez","xwoba":0.367,"pa":60,"type":"pitcher"},"682995":{"name":"Hunter Barco","xwoba":0.391,"pa":60,"type":"pitcher"},"641401":{"name":"Connor Brogdon","xwoba":0.315,"pa":60,"type":"pitcher"},"676534":{"name":"Calvin Faucher","xwoba":0.352,"pa":60,"type":"pitcher"},"668390":{"name":"Cole Winn","xwoba":0.308,"pa":60,"type":"pitcher"},"669438":{"name":"Mason Englert","xwoba":0.441,"pa":60,"type":"pitcher"},"621112":{"name":"Paul Blackburn","xwoba":0.301,"pa":60,"type":"pitcher"},"621237":{"name":"Jos\u00e9 Alvarado","xwoba":0.293,"pa":60,"type":"pitcher"},"663158":{"name":"Robert Suarez","xwoba":0.252,"pa":59,"type":"pitcher"},"683742":{"name":"Jose Franco","xwoba":0.37,"pa":59,"type":"pitcher"},"607481":{"name":"Aaron Bummer","xwoba":0.385,"pa":59,"type":"pitcher"},"641745":{"name":"Brad Keller","xwoba":0.273,"pa":59,"type":"pitcher"},"694851":{"name":"Andrew Hoffmann","xwoba":0.338,"pa":59,"type":"pitcher"},"675660":{"name":"Shane Drohan","xwoba":0.302,"pa":59,"type":"pitcher"},"596133":{"name":"Luke Weaver","xwoba":0.32,"pa":58,"type":"pitcher"},"621381":{"name":"Matt Strahm","xwoba":0.243,"pa":58,"type":"pitcher"},"596001":{"name":"Jakob Junis","xwoba":0.301,"pa":58,"type":"pitcher"},"664991":{"name":"Grant Wolfram","xwoba":0.264,"pa":58,"type":"pitcher"},"695243":{"name":"Mason Miller","xwoba":0.122,"pa":58,"type":"pitcher"},"682254":{"name":"Mason Montgomery","xwoba":0.295,"pa":58,"type":"pitcher"},"681892":{"name":"Kody Funderburk","xwoba":0.373,"pa":58,"type":"pitcher"},"681402":{"name":"Gus Varland","xwoba":0.333,"pa":58,"type":"pitcher"},"572955":{"name":"Pierce Johnson","xwoba":0.42,"pa":57,"type":"pitcher"},"573009":{"name":"Joe Mantiply","xwoba":0.327,"pa":57,"type":"pitcher"},"657514":{"name":"Brennan Bernardino","xwoba":0.289,"pa":57,"type":"pitcher"},"681870":{"name":"Erik Sabrowski","xwoba":0.26,"pa":57,"type":"pitcher"},"667463":{"name":"John King","xwoba":0.246,"pa":56,"type":"pitcher"},"657424":{"name":"Matt Gage","xwoba":0.316,"pa":56,"type":"pitcher"},"689254":{"name":"Mason Fluharty","xwoba":0.237,"pa":56,"type":"pitcher"},"687606":{"name":"Paxton Schultz","xwoba":0.351,"pa":56,"type":"pitcher"},"681867":{"name":"Cooper Criswell","xwoba":0.318,"pa":56,"type":"pitcher"},"642100":{"name":"Gabe Speier","xwoba":0.337,"pa":56,"type":"pitcher"},"675989":{"name":"Cody Bolton","xwoba":0.392,"pa":56,"type":"pitcher"},"687570":{"name":"Connor Prielipp","xwoba":0.296,"pa":56,"type":"pitcher"},"678022":{"name":"Jack Perkins","xwoba":0.294,"pa":55,"type":"pitcher"},"681895":{"name":"Evan Sisk","xwoba":0.251,"pa":55,"type":"pitcher"},"687330":{"name":"Kevin Kelly","xwoba":0.309,"pa":55,"type":"pitcher"},"680730":{"name":"Mitchell Parker","xwoba":0.316,"pa":55,"type":"pitcher"},"666808":{"name":"Camilo Doval","xwoba":0.276,"pa":55,"type":"pitcher"},"670167":{"name":"John Schreiber","xwoba":0.36,"pa":55,"type":"pitcher"},"672582":{"name":"Angel Zerpa","xwoba":0.407,"pa":55,"type":"pitcher"},"663738":{"name":"Daniel Lynch IV","xwoba":0.248,"pa":55,"type":"pitcher"},"806960":{"name":"Luis Morales","xwoba":0.474,"pa":55,"type":"pitcher"},"657044":{"name":"Ryan Thompson","xwoba":0.315,"pa":54,"type":"pitcher"},"656848":{"name":"Michael Petersen","xwoba":0.298,"pa":54,"type":"pitcher"},"681217":{"name":"Chase Silseth","xwoba":0.335,"pa":54,"type":"pitcher"},"689147":{"name":"Orion Kerkering","xwoba":0.227,"pa":54,"type":"pitcher"},"670329":{"name":"Rico Garcia","xwoba":0.22,"pa":54,"type":"pitcher"},"665622":{"name":"Luis Medina","xwoba":0.368,"pa":54,"type":"pitcher"},"676775":{"name":"Keaton Winn","xwoba":0.208,"pa":54,"type":"pitcher"},"642207":{"name":"Devin Williams","xwoba":0.298,"pa":53,"type":"pitcher"},"656730":{"name":"Trevor Megill","xwoba":0.31,"pa":53,"type":"pitcher"},"641329":{"name":"Bryan Baker","xwoba":0.211,"pa":53,"type":"pitcher"},"676684":{"name":"Will Vest","xwoba":0.289,"pa":52,"type":"pitcher"},"656945":{"name":"Tanner Scott","xwoba":0.309,"pa":52,"type":"pitcher"},"621366":{"name":"Ryan Borucki","xwoba":0.323,"pa":51,"type":"pitcher"},"677161":{"name":"Zack Kelly","xwoba":0.365,"pa":51,"type":"pitcher"},"815083":{"name":"Mitch Farris","xwoba":0.343,"pa":51,"type":"pitcher"},"657612":{"name":"Tim Hill","xwoba":0.282,"pa":51,"type":"pitcher"},"682842":{"name":"Abner Uribe","xwoba":0.288,"pa":50,"type":"pitcher"},"701552":{"name":"Andre Granillo","xwoba":0.396,"pa":50,"type":"pitcher"},"683232":{"name":"Nick Mears","xwoba":0.364,"pa":50,"type":"pitcher"},"676467":{"name":"Colton Gordon","xwoba":0.41,"pa":50,"type":"pitcher"},"663485":{"name":"Cole Sands","xwoba":0.327,"pa":50,"type":"pitcher"},"681343":{"name":"Shane Smith","xwoba":0.335,"pa":49,"type":"pitcher"},"669270":{"name":"Joel Kuhnel","xwoba":0.336,"pa":49,"type":"pitcher"},"656234":{"name":"Jake Bird","xwoba":0.289,"pa":49,"type":"pitcher"},"657756":{"name":"Connor Seabold","xwoba":0.263,"pa":49,"type":"pitcher"},"548384":{"name":"Brooks Raley","xwoba":0.291,"pa":49,"type":"pitcher"},"681911":{"name":"Alex Vesia","xwoba":0.264,"pa":48,"type":"pitcher"},"664299":{"name":"Cristian Javier","xwoba":0.407,"pa":48,"type":"pitcher"},"669062":{"name":"Erik Miller","xwoba":0.232,"pa":48,"type":"pitcher"},"472610":{"name":"Luis Garc\u00eda","xwoba":0.412,"pa":48,"type":"pitcher"},"678368":{"name":"Valente Bellozo","xwoba":0.476,"pa":48,"type":"pitcher"},"685801":{"name":"Hunter Bigge","xwoba":0.309,"pa":47,"type":"pitcher"},"694918":{"name":"Blade Tidwell","xwoba":0.296,"pa":47,"type":"pitcher"},"542888":{"name":"Shawn Armstrong","xwoba":0.343,"pa":47,"type":"pitcher"},"608371":{"name":"Lucas Sims","xwoba":0.332,"pa":46,"type":"pitcher"},"642232":{"name":"Ryan Yarbrough","xwoba":0.26,"pa":46,"type":"pitcher"},"683618":{"name":"Edgardo Henriquez","xwoba":0.318,"pa":46,"type":"pitcher"},"682120":{"name":"Tim Herrin","xwoba":0.261,"pa":46,"type":"pitcher"},"690925":{"name":"Clayton Beeter","xwoba":0.341,"pa":46,"type":"pitcher"},"664854":{"name":"Ryan Helsley","xwoba":0.271,"pa":46,"type":"pitcher"},"669212":{"name":"Eli Morgan","xwoba":0.375,"pa":45,"type":"pitcher"},"701719":{"name":"Tyler Samaniego","xwoba":0.326,"pa":45,"type":"pitcher"},"670059":{"name":"Colin Holderman","xwoba":0.286,"pa":45,"type":"pitcher"},"663465":{"name":"Kolby Allard","xwoba":0.386,"pa":45,"type":"pitcher"},"800311":{"name":"Didier Fuentes","xwoba":0.309,"pa":45,"type":"pitcher"},"595014":{"name":"Blake Treinen","xwoba":0.382,"pa":44,"type":"pitcher"},"679883":{"name":"Luinder Avila","xwoba":0.412,"pa":44,"type":"pitcher"},"837227":{"name":"Tatsuya Imai","xwoba":0.321,"pa":44,"type":"pitcher"},"547973":{"name":"Aroldis Chapman","xwoba":0.325,"pa":44,"type":"pitcher"},"665660":{"name":"Elvis Alvarado","xwoba":0.412,"pa":44,"type":"pitcher"},"695684":{"name":"Elmer Rodr\u00edguez","xwoba":0.414,"pa":44,"type":"pitcher"},"623149":{"name":"Paul Sewald","xwoba":0.305,"pa":44,"type":"pitcher"},"686613":{"name":"Hunter Brown","xwoba":0.216,"pa":43,"type":"pitcher"},"665152":{"name":"Dean Kremer","xwoba":0.321,"pa":43,"type":"pitcher"},"554430":{"name":"Zack Wheeler","xwoba":0.25,"pa":43,"type":"pitcher"},"666974":{"name":"Yennier Cano","xwoba":0.303,"pa":43,"type":"pitcher"},"685005":{"name":"Christian Roa","xwoba":0.418,"pa":43,"type":"pitcher"},"605447":{"name":"Jordan Romano","xwoba":0.328,"pa":42,"type":"pitcher"},"572143":{"name":"Burch Smith","xwoba":0.267,"pa":42,"type":"pitcher"},"663767":{"name":"Chase Shugart","xwoba":0.28,"pa":42,"type":"pitcher"},"693312":{"name":"Kyle Nicolas","xwoba":0.437,"pa":42,"type":"pitcher"},"679775":{"name":"Kyle Backhus","xwoba":0.274,"pa":41,"type":"pitcher"},"664126":{"name":"Pete Fairbanks","xwoba":0.297,"pa":41,"type":"pitcher"},"664208":{"name":"Phil Maton","xwoba":0.385,"pa":40,"type":"pitcher"},"686610":{"name":"Ken Waldichuk","xwoba":0.399,"pa":40,"type":"pitcher"},"615698":{"name":"Cal Quantrill","xwoba":0.358,"pa":40,"type":"pitcher"},"702056":{"name":"Trey Yesavage","xwoba":0.201,"pa":40,"type":"pitcher"},"680704":{"name":"Nick Sandlin","xwoba":0.378,"pa":40,"type":"pitcher"},"669093":{"name":"Jeremiah Estrada","xwoba":0.329,"pa":39,"type":"pitcher"},"592094":{"name":"Jason Adam","xwoba":0.24,"pa":39,"type":"pitcher"},"680742":{"name":"Jonathan Bowlan","xwoba":0.274,"pa":39,"type":"pitcher"},"671382":{"name":"Cameron Foster","xwoba":0.279,"pa":39,"type":"pitcher"},"666374":{"name":"Matt Brash","xwoba":0.308,"pa":38,"type":"pitcher"},"573204":{"name":"Caleb Thielbar","xwoba":0.25,"pa":37,"type":"pitcher"},"445276":{"name":"Kenley Jansen","xwoba":0.359,"pa":37,"type":"pitcher"},"664353":{"name":"Jos\u00e9 Urquidy","xwoba":0.314,"pa":36,"type":"pitcher"},"543056":{"name":"Danny Coulombe","xwoba":0.34,"pa":36,"type":"pitcher"},"606303":{"name":"Joel Payamps","xwoba":0.378,"pa":36,"type":"pitcher"},"669371":{"name":"Cole Henry","xwoba":0.334,"pa":35,"type":"pitcher"},"628452":{"name":"Raisel Iglesias","xwoba":0.178,"pa":35,"type":"pitcher"},"676395":{"name":"Robert Garcia","xwoba":0.335,"pa":34,"type":"pitcher"},"621242":{"name":"Edwin D\u00edaz","xwoba":0.333,"pa":33,"type":"pitcher"},"681252":{"name":"Jack Anderson","xwoba":0.373,"pa":32,"type":"pitcher"},"702303":{"name":"Riley Martin","xwoba":0.251,"pa":32,"type":"pitcher"},"669020":{"name":"Ryan Rolison","xwoba":0.254,"pa":32,"type":"pitcher"},"669684":{"name":"Chris Murphy","xwoba":0.32,"pa":32,"type":"pitcher"},"691946":{"name":"George Klassen","xwoba":0.474,"pa":32,"type":"pitcher"},"683769":{"name":"Hunter Gaddis","xwoba":0.321,"pa":31,"type":"pitcher"},"661395":{"name":"Jhoan Duran","xwoba":0.283,"pa":31,"type":"pitcher"},"647315":{"name":"Zach Pop","xwoba":0.319,"pa":31,"type":"pitcher"},"641585":{"name":"J.P. France","xwoba":0.422,"pa":31,"type":"pitcher"},"518886":{"name":"Craig Kimbrel","xwoba":0.282,"pa":30,"type":"pitcher"},"701656":{"name":"Logan Henderson","xwoba":0.191,"pa":30,"type":"pitcher"},"686560":{"name":"Gavin Collyer","xwoba":0.253,"pa":29,"type":"pitcher"},"681035":{"name":"Christian Scott","xwoba":0.34,"pa":29,"type":"pitcher"},"455119":{"name":"Chris Martin","xwoba":0.398,"pa":29,"type":"pitcher"},"669165":{"name":"Kyle Hurt","xwoba":0.186,"pa":29,"type":"pitcher"},"670183":{"name":"Garrett Acton","xwoba":0.252,"pa":28,"type":"pitcher"},"681151":{"name":"Jayden Murray","xwoba":0.285,"pa":28,"type":"pitcher"},"608650":{"name":"Dietrich Enns","xwoba":0.358,"pa":27,"type":"pitcher"},"682608":{"name":"Peyton Gray","xwoba":0.395,"pa":27,"type":"pitcher"},"691945":{"name":"Carter Baumler","xwoba":0.361,"pa":27,"type":"pitcher"},"674444":{"name":"Steven Cruz","xwoba":0.395,"pa":26,"type":"pitcher"},"681676":{"name":"Ryan Fernandez","xwoba":0.258,"pa":26,"type":"pitcher"},"691951":{"name":"Sam Aldegheri","xwoba":0.423,"pa":26,"type":"pitcher"},"690990":{"name":"Cade Horton","xwoba":0.283,"pa":26,"type":"pitcher"},"689520":{"name":"Cody Laweryson","xwoba":0.301,"pa":26,"type":"pitcher"},"605218":{"name":"Carl Edwards Jr.","xwoba":0.26,"pa":25,"type":"pitcher"},"696062":{"name":"Wilber Dotel","xwoba":0.294,"pa":25,"type":"pitcher"},"681810":{"name":"Austin Warren","xwoba":0.239,"pa":25,"type":"pitcher"},"688297":{"name":"Chris Roycroft","xwoba":0.353,"pa":25,"type":"pitcher"},"682610":{"name":"Roddery Mu\u00f1oz","xwoba":0.443,"pa":25,"type":"pitcher"},"694363":{"name":"Jared Shuster","xwoba":0.226,"pa":25,"type":"pitcher"},"669724":{"name":"Brenan Hanifee","xwoba":0.258,"pa":25,"type":"pitcher"},"552640":{"name":"Andrew Kittredge","xwoba":0.272,"pa":24,"type":"pitcher"},"664192":{"name":"Joey Lucchesi","xwoba":0.443,"pa":24,"type":"pitcher"},"663893":{"name":"Brendon Little","xwoba":0.408,"pa":24,"type":"pitcher"},"686790":{"name":"Trevor McDonald","xwoba":0.269,"pa":24,"type":"pitcher"},"694037":{"name":"Daniel Palencia","xwoba":0.322,"pa":23,"type":"pitcher"},"676508":{"name":"Ben Casparius","xwoba":0.386,"pa":23,"type":"pitcher"},"695534":{"name":"Chase Petty","xwoba":0.385,"pa":23,"type":"pitcher"},"605452":{"name":"Joe Ross","xwoba":0.469,"pa":22,"type":"pitcher"},"656686":{"name":"Corbin Martin","xwoba":0.348,"pa":22,"type":"pitcher"},"547184":{"name":"Michael Kelly","xwoba":0.382,"pa":22,"type":"pitcher"},"696131":{"name":"Mason Black","xwoba":0.351,"pa":22,"type":"pitcher"},"663568":{"name":"Stephen Kolek","xwoba":0.298,"pa":22,"type":"pitcher"},"669211":{"name":"Keegan Akin","xwoba":0.403,"pa":22,"type":"pitcher"},"686751":{"name":"Seth Johnson","xwoba":0.364,"pa":21,"type":"pitcher"},"694680":{"name":"Trevor Martin","xwoba":0.369,"pa":21,"type":"pitcher"},"689441":{"name":"Coleman Crow","xwoba":0.334,"pa":21,"type":"pitcher"},"696270":{"name":"Ryan Johnson","xwoba":0.362,"pa":21,"type":"pitcher"},"681168":{"name":"Luis Curvelo","xwoba":0.328,"pa":21,"type":"pitcher"},"687765":{"name":"Mitch Spence","xwoba":0.373,"pa":21,"type":"pitcher"},"694346":{"name":"Trey Gibson","xwoba":0.431,"pa":21,"type":"pitcher"},"680744":{"name":"Ty Madden","xwoba":0.166,"pa":20,"type":"pitcher"},"663559":{"name":"Bailey Falter","xwoba":0.295,"pa":20,"type":"pitcher"},"687562":{"name":"Jake Bennett","xwoba":0.465,"pa":20,"type":"pitcher"},"687849":{"name":"Zak Kent","xwoba":0.48,"pa":20,"type":"pitcher"},"690928":{"name":"Hunter Dobbins","xwoba":0.356,"pa":19,"type":"pitcher"},"670950":{"name":"Trevor Richards","xwoba":0.325,"pa":19,"type":"pitcher"},"675911":{"name":"Spencer Strider","xwoba":0.38,"pa":19,"type":"pitcher"},"656288":{"name":"Griffin Canning","xwoba":0.32,"pa":19,"type":"pitcher"},"434378":{"name":"Justin Verlander","xwoba":0.475,"pa":19,"type":"pitcher"},"676596":{"name":"Josh Fleming","xwoba":0.472,"pa":18,"type":"pitcher"},"642759":{"name":"Julian Fern\u00e1ndez","xwoba":0.302,"pa":18,"type":"pitcher"},"664076":{"name":"Garrett Cleavinger","xwoba":0.366,"pa":18,"type":"pitcher"},"702153":{"name":"Brian Fitzpatrick","xwoba":0.298,"pa":18,"type":"pitcher"},"670912":{"name":"Johan Oviedo","xwoba":0.485,"pa":18,"type":"pitcher"},"820862":{"name":"Jos\u00e9 Fermin","xwoba":0.272,"pa":18,"type":"pitcher"},"640451":{"name":"Hunter Harvey","xwoba":0.345,"pa":18,"type":"pitcher"},"692230":{"name":"Carlos Rodriguez","xwoba":0.183,"pa":17,"type":"pitcher"},"656986":{"name":"Bennett Sousa","xwoba":0.379,"pa":17,"type":"pitcher"},"656212":{"name":"Charlie Barnes","xwoba":0.393,"pa":17,"type":"pitcher"},"621107":{"name":"Zach Eflin","xwoba":0.308,"pa":17,"type":"pitcher"},"695380":{"name":"Alex Hoppe","xwoba":0.341,"pa":17,"type":"pitcher"},"699823":{"name":"Tyler Davis","xwoba":0.156,"pa":17,"type":"pitcher"},"676130":{"name":"Jos\u00e9 Butt\u00f3","xwoba":0.496,"pa":16,"type":"pitcher"},"689266":{"name":"Dylan Dodd","xwoba":0.242,"pa":16,"type":"pitcher"},"699151":{"name":"Jedixson Paez","xwoba":0.494,"pa":16,"type":"pitcher"},"674841":{"name":"Andrew Alvarez","xwoba":0.243,"pa":16,"type":"pitcher"},"671109":{"name":"Jake Eder","xwoba":0.46,"pa":15,"type":"pitcher"},"688497":{"name":"Taylor Rashi","xwoba":0.327,"pa":15,"type":"pitcher"},"676742":{"name":"Cam Sanders","xwoba":0.24,"pa":15,"type":"pitcher"},"676510":{"name":"Nolan Hoffman","xwoba":0.308,"pa":15,"type":"pitcher"},"687377":{"name":"Orlando Ribalta","xwoba":0.219,"pa":15,"type":"pitcher"},"656457":{"name":"Tyler Gilbert","xwoba":0.545,"pa":15,"type":"pitcher"},"685126":{"name":"Brandon Eisert","xwoba":0.386,"pa":14,"type":"pitcher"},"686580":{"name":"Justin Slaten","xwoba":0.254,"pa":14,"type":"pitcher"},"681751":{"name":"Lazaro Estrada","xwoba":0.274,"pa":14,"type":"pitcher"},"675919":{"name":"Nick Raquet","xwoba":0.443,"pa":14,"type":"pitcher"},"669620":{"name":"Brady Basso","xwoba":0.503,"pa":14,"type":"pitcher"},"666619":{"name":"Gregory Santos","xwoba":0.423,"pa":14,"type":"pitcher"},"676568":{"name":"Ricky Vanasco","xwoba":0.291,"pa":13,"type":"pitcher"},"657649":{"name":"Jared Koenig","xwoba":0.23,"pa":13,"type":"pitcher"},"683409":{"name":"Angel Chivilli","xwoba":0.395,"pa":13,"type":"pitcher"},"682825":{"name":"Luis Mey","xwoba":0.327,"pa":13,"type":"pitcher"},"682274":{"name":"Yaramil Hiraldo","xwoba":0.519,"pa":12,"type":"pitcher"},"683000":{"name":"Riley Cornelio","xwoba":0.425,"pa":12,"type":"pitcher"},"606965":{"name":"Chris Devenski","xwoba":0.297,"pa":12,"type":"pitcher"},"671131":{"name":"Jackson Rutledge","xwoba":0.42,"pa":12,"type":"pitcher"},"608723":{"name":"Austin Voth","xwoba":0.284,"pa":12,"type":"pitcher"},"660604":{"name":"Alan Rangel","xwoba":0.273,"pa":12,"type":"pitcher"},"691548":{"name":"Rolddy Mu\u00f1oz","xwoba":0.429,"pa":12,"type":"pitcher"},"700413":{"name":"Tyler Uberstine","xwoba":0.379,"pa":11,"type":"pitcher"},"806188":{"name":"Cade Gibson","xwoba":0.46,"pa":11,"type":"pitcher"},"669920":{"name":"Jason Alexander","xwoba":0.371,"pa":11,"type":"pitcher"},"681799":{"name":"Ethan Roberts","xwoba":0.357,"pa":10,"type":"pitcher"},"700842":{"name":"Eduardo Rivera","xwoba":0.187,"pa":10,"type":"pitcher"},"664074":{"name":"Cody Ponce","xwoba":0.244,"pa":10,"type":"pitcher"},"642152":{"name":"Lou Trivino","xwoba":0.52,"pa":9,"type":"pitcher"},"680702":{"name":"Joey Gerber","xwoba":0.264,"pa":9,"type":"pitcher"},"805299":{"name":"Brandyn Garcia","xwoba":0.155,"pa":9,"type":"pitcher"},"689690":{"name":"Alek Jacob","xwoba":0.342,"pa":9,"type":"pitcher"},"686930":{"name":"Mason Barnett","xwoba":0.312,"pa":9,"type":"pitcher"},"660787":{"name":"Yerry De los Santos","xwoba":0.347,"pa":9,"type":"pitcher"},"680951":{"name":"Doug Nikhazy","xwoba":0.293,"pa":9,"type":"pitcher"},"687209":{"name":"Zach Maxwell","xwoba":0.72,"pa":8,"type":"pitcher"},"592826":{"name":"Vince Velasquez","xwoba":0.132,"pa":8,"type":"pitcher"},"678020":{"name":"Seth Halvorsen","xwoba":0.368,"pa":8,"type":"pitcher"},"696070":{"name":"Kendry Rojas","xwoba":0.523,"pa":8,"type":"pitcher"},"691769":{"name":"Philip Abner","xwoba":0.238,"pa":8,"type":"pitcher"},"621053":{"name":"Tyler Ferguson","xwoba":0.641,"pa":8,"type":"pitcher"},"471911":{"name":"Carlos Carrasco","xwoba":0.252,"pa":8,"type":"pitcher"},"608032":{"name":"Carlos Est\u00e9vez","xwoba":0.631,"pa":7,"type":"pitcher"},"641656":{"name":"Ian Hamilton","xwoba":0.466,"pa":7,"type":"pitcher"},"690155":{"name":"Matt Pushard","xwoba":0.411,"pa":7,"type":"pitcher"},"805326":{"name":"Tyler Schweitzer","xwoba":0.295,"pa":7,"type":"pitcher"},"668834":{"name":"Easton McGee","xwoba":0.416,"pa":6,"type":"pitcher"},"694795":{"name":"Josh Ekness","xwoba":0.327,"pa":6,"type":"pitcher"},"683627":{"name":"Anthony Molina","xwoba":0.283,"pa":6,"type":"pitcher"},"695445":{"name":"Chase Lee","xwoba":0.298,"pa":5,"type":"pitcher"},"605441":{"name":"Yacksel R\u00edos","xwoba":0.335,"pa":5,"type":"pitcher"},"681432":{"name":"Luke Little","xwoba":0.527,"pa":5,"type":"pitcher"},"664744":{"name":"Jose Espada","xwoba":0.34,"pa":4,"type":"pitcher"},"689546":{"name":"Nick Davila","xwoba":0.373,"pa":4,"type":"pitcher"},"666711":{"name":"Joel Peguero","xwoba":0.124,"pa":4,"type":"pitcher"},"642048":{"name":"Tayler Saucedo","xwoba":0.246,"pa":3,"type":"pitcher"},"676702":{"name":"Hunter Stratton","xwoba":0.191,"pa":3,"type":"pitcher"},"686563":{"name":"Jonathan Cannon","xwoba":0.707,"pa":3,"type":"pitcher"},"687473":{"name":"Ryan Gusto","xwoba":0.579,"pa":3,"type":"pitcher"},"687531":{"name":"William Kempner","xwoba":0.117,"pa":3,"type":"pitcher"},"804619":{"name":"John Klein","xwoba":0.063,"pa":3,"type":"pitcher"},"687941":{"name":"Alec Gamboa","xwoba":0.061,"pa":3,"type":"pitcher"},"701474":{"name":"Duncan Davitt","xwoba":0.669,"pa":3,"type":"pitcher"}}}